[
  { "id": 19
    ,"yyyymm": "2024/11"
    ,"basedate": "2024/11/12"
    ,"holding": false
    ,"check": false
    ,"name": "ベヒモス"
    ,"name_s": "ベヒモス"
    ,"icon": "ベヒモス"
    ,"weakPoint": "電撃"
    ,"dataList": [
       { "datetime": "1900-01-00 23:19:52", "days": 0, "rank": 0.04, "score": 8877 }
      ,{ "datetime": "1900-01-00 23:44:06", "days": 0, "rank": 0.43, "score": 6102 }
      ,{ "datetime": "1900-01-02 23:51:48", "days": 2, "rank": 0, "score": 12473 }
      ,{ "datetime": "1900-01-02 17:17:21", "days": 2, "rank": 0, "score": 11904 }
      ,{ "datetime": "1900-01-02 21:52:54", "days": 2, "rank": 0, "score": 11092 }
      ,{ "datetime": "1900-01-03 00:50:22", "days": 2, "rank": 0.01, "score": 11022 }
      ,{ "datetime": "1900-01-02 21:19:49", "days": 2, "rank": 0, "score": 10540 }
      ,{ "datetime": "1900-01-02 20:01:29", "days": 2, "rank": 0, "score": 10440 }
      ,{ "datetime": "1900-01-02 14:49:35", "days": 2, "rank": 0, "score": 10305 }
      ,{ "datetime": "1900-01-03 00:07:12", "days": 2, "rank": 0.01, "score": 10148 }
      ,{ "datetime": "1900-01-03 02:00:11", "days": 2, "rank": 0.02, "score": 9644 }
      ,{ "datetime": "1900-01-02 21:57:36", "days": 2, "rank": 0.01, "score": 9601 }
      ,{ "datetime": "1900-01-02 20:25:08", "days": 2, "rank": 0.01, "score": 9582 }
      ,{ "datetime": "1900-01-02 15:06:17", "days": 2, "rank": 0, "score": 9373 }
      ,{ "datetime": "1900-01-03 01:44:53", "days": 2, "rank": 0.03, "score": 9057 }
      ,{ "datetime": "1900-01-03 04:29:08", "days": 2, "rank": 0.05, "score": 8747 }
      ,{ "datetime": "1900-01-03 01:37:53", "days": 2, "rank": 0.05, "score": 8727 }
      ,{ "datetime": "1900-01-02 13:55:09", "days": 2, "rank": 0, "score": 8717 }
      ,{ "datetime": "1900-01-02 23:50:04", "days": 2, "rank": 0.04, "score": 8668 }
      ,{ "datetime": "1900-01-02 13:53:24", "days": 2, "rank": 0, "score": 8620 }
      ,{ "datetime": "1900-01-03 01:54:41", "days": 2, "rank": 0.05, "score": 8620 }
      ,{ "datetime": "1900-01-02 22:12:51", "days": 2, "rank": 0.03, "score": 8436 }
      ,{ "datetime": "1900-01-02 19:39:23", "days": 2, "rank": 0.02, "score": 8319 }
      ,{ "datetime": "1900-01-02 21:34:43", "days": 2, "rank": 0.03, "score": 8301 }
      ,{ "datetime": "1900-01-02 17:04:37", "days": 2, "rank": 0.02, "score": 8283 }
      ,{ "datetime": "1900-01-03 00:55:54", "days": 2, "rank": 0.07, "score": 7924 }
      ,{ "datetime": "1900-01-02 19:46:27", "days": 2, "rank": 0.04, "score": 7826 }
      ,{ "datetime": "1900-01-02 17:23:16", "days": 2, "rank": 0.03, "score": 7820 }
      ,{ "datetime": "1900-01-02 17:05:19", "days": 2, "rank": 0.03, "score": 7802 }
      ,{ "datetime": "1900-01-02 21:24:31", "days": 2, "rank": 0.05, "score": 7782 }
      ,{ "datetime": "1900-01-02 15:45:58", "days": 2, "rank": 0.02, "score": 7765 }
      ,{ "datetime": "1900-01-03 01:43:45", "days": 2, "rank": 0.1, "score": 7675 }
      ,{ "datetime": "1900-01-02 16:25:35", "days": 2, "rank": 0.02, "score": 7632 }
      ,{ "datetime": "1900-01-03 01:20:02", "days": 2, "rank": 0.1, "score": 7592 }
      ,{ "datetime": "1900-01-02 23:53:38", "days": 2, "rank": 0.09, "score": 7591 }
      ,{ "datetime": "1900-01-02 18:33:06", "days": 2, "rank": 0.05, "score": 7500 }
      ,{ "datetime": "1900-01-02 22:51:25", "days": 2, "rank": 0.08, "score": 7491 }
      ,{ "datetime": "1900-01-02 22:39:43", "days": 2, "rank": 0.08, "score": 7483 }
      ,{ "datetime": "1900-01-02 19:52:11", "days": 2, "rank": 0.05, "score": 7433 }
      ,{ "datetime": "1900-01-02 19:48:01", "days": 2, "rank": 0.06, "score": 7433 }
      ,{ "datetime": "1900-01-02 17:59:52", "days": 2, "rank": 0.05, "score": 7428 }
      ,{ "datetime": "1900-01-03 01:16:30", "days": 2, "rank": 0.12, "score": 7410 }
      ,{ "datetime": "1900-01-02 12:00:00", "days": 2, "rank": 0, "score": 7372 }
      ,{ "datetime": "1900-01-02 23:52:13", "days": 2, "rank": 0.1, "score": 7366 }
      ,{ "datetime": "1900-01-02 19:06:53", "days": 2, "rank": 0.06, "score": 7361 }
      ,{ "datetime": "1900-01-02 13:15:43", "days": 2, "rank": 0.01, "score": 7314 }
      ,{ "datetime": "1900-01-02 16:00:15", "days": 2, "rank": 0.03, "score": 7309 }
      ,{ "datetime": "1900-01-02 22:15:34", "days": 2, "rank": 0.09, "score": 7275 }
      ,{ "datetime": "1900-01-02 19:31:54", "days": 2, "rank": 0.06, "score": 7162 }
      ,{ "datetime": "1900-01-02 23:09:14", "days": 2, "rank": 0.12, "score": 7081 }
      ,{ "datetime": "1900-01-02 12:00:00", "days": 2, "rank": 0, "score": 7031 }
      ,{ "datetime": "1900-01-02 20:24:13", "days": 2, "rank": 0.08, "score": 6989 }
      ,{ "datetime": "1900-01-03 00:25:59", "days": 2, "rank": 0.16, "score": 6964 }
      ,{ "datetime": "1900-01-02 21:15:24", "days": 2, "rank": 0.1, "score": 6952 }
      ,{ "datetime": "1900-01-02 23:55:21", "days": 2, "rank": 0.15, "score": 6947 }
      ,{ "datetime": "1900-01-03 04:28:57", "days": 2, "rank": 0.21, "score": 6849 }
      ,{ "datetime": "1900-01-02 23:13:25", "days": 2, "rank": 0.15, "score": 6834 }
      ,{ "datetime": "1900-01-03 01:40:42", "days": 2, "rank": 0.11, "score": 6802 }
      ,{ "datetime": "1900-01-02 18:19:17", "days": 2, "rank": 0.07, "score": 6768 }
      ,{ "datetime": "1900-01-02 17:17:35", "days": 2, "rank": 0.06, "score": 6745 }
      ,{ "datetime": "1900-01-02 15:35:13", "days": 2, "rank": 0.05, "score": 6731 }
      ,{ "datetime": "1900-01-02 21:50:54", "days": 2, "rank": 0.13, "score": 6640 }
      ,{ "datetime": "1900-01-02 12:00:00", "days": 2, "rank": 0, "score": 6637 }
      ,{ "datetime": "1900-01-02 16:02:54", "days": 2, "rank": 0.05, "score": 6605 }
      ,{ "datetime": "1900-01-02 23:42:45", "days": 2, "rank": 0.2, "score": 6590 }
      ,{ "datetime": "1900-01-02 18:33:20", "days": 2, "rank": 0.09, "score": 6582 }
      ,{ "datetime": "1900-01-03 01:27:49", "days": 2, "rank": 0.25, "score": 6580 }
      ,{ "datetime": "1900-01-03 00:47:00", "days": 2, "rank": 0.23, "score": 6576 }
      ,{ "datetime": "1900-01-02 19:44:44", "days": 2, "rank": 0.11, "score": 6550 }
      ,{ "datetime": "1900-01-03 02:02:04", "days": 2, "rank": 0.27, "score": 6531 }
      ,{ "datetime": "1900-01-02 18:48:14", "days": 2, "rank": 0.09, "score": 6526 }
      ,{ "datetime": "1900-01-03 00:48:00", "days": 2, "rank": 0.25, "score": 6516 }
      ,{ "datetime": "1900-01-02 13:53:18", "days": 2, "rank": 0.02, "score": 6510 }
      ,{ "datetime": "1900-01-02 19:52:51", "days": 2, "rank": 0.12, "score": 6501 }
      ,{ "datetime": "1900-01-02 22:47:16", "days": 2, "rank": 0.17, "score": 6497 }
      ,{ "datetime": "1900-01-03 02:49:43", "days": 2, "rank": 0.28, "score": 6484 }
      ,{ "datetime": "1900-01-02 22:05:06", "days": 2, "rank": 0.18, "score": 6456 }
      ,{ "datetime": "1900-01-02 15:06:06", "days": 2, "rank": 0.06, "score": 6434 }
      ,{ "datetime": "1900-01-02 21:25:37", "days": 2, "rank": 0.17, "score": 6390 }
      ,{ "datetime": "1900-01-02 20:06:29", "days": 2, "rank": 0.14, "score": 6388 }
      ,{ "datetime": "1900-01-02 20:37:38", "days": 2, "rank": 0.15, "score": 6376 }
      ,{ "datetime": "1900-01-02 21:03:27", "days": 2, "rank": 0.15, "score": 6374 }
      ,{ "datetime": "1900-01-03 00:35:05", "days": 2, "rank": 0.29, "score": 6348 }
      ,{ "datetime": "1900-01-02 23:31:08", "days": 2, "rank": 0.25, "score": 6320 }
      ,{ "datetime": "1900-01-02 16:35:56", "days": 2, "rank": 0.08, "score": 6313 }
      ,{ "datetime": "1900-01-02 12:58:39", "days": 2, "rank": 0.01, "score": 6303 }
      ,{ "datetime": "1900-01-02 15:11:35", "days": 2, "rank": 0.02, "score": 6278 }
      ,{ "datetime": "1900-01-03 00:07:00", "days": 2, "rank": 0.3, "score": 6269 }
      ,{ "datetime": "1900-01-03 00:02:43", "days": 2, "rank": 0.29, "score": 6262 }
      ,{ "datetime": "1900-01-02 13:53:33", "days": 2, "rank": 0.03, "score": 6260 }
      ,{ "datetime": "1900-01-02 21:10:00", "days": 2, "rank": 0.18, "score": 6251 }
      ,{ "datetime": "1900-01-02 18:01:52", "days": 2, "rank": 0.11, "score": 6233 }
      ,{ "datetime": "1900-01-02 21:53:03", "days": 2, "rank": 0.22, "score": 6219 }
      ,{ "datetime": "1900-01-02 16:24:49", "days": 2, "rank": 0.08, "score": 6213 }
      ,{ "datetime": "1900-01-02 21:32:26", "days": 2, "rank": 0.22, "score": 6177 }
      ,{ "datetime": "1900-01-02 13:48:26", "days": 2, "rank": 0.03, "score": 6140 }
      ,{ "datetime": "1900-01-02 12:49:31", "days": 2, "rank": 0.01, "score": 6140 }
      ,{ "datetime": "1900-01-02 19:24:41", "days": 2, "rank": 0.15, "score": 6137 }
      ,{ "datetime": "1900-01-02 19:50:04", "days": 2, "rank": 0.16, "score": 6130 }
      ,{ "datetime": "1900-01-02 17:27:37", "days": 2, "rank": 0.11, "score": 6125 }
      ,{ "datetime": "1900-01-02 22:04:21", "days": 2, "rank": 0.25, "score": 6123 }
      ,{ "datetime": "1900-01-02 20:38:00", "days": 2, "rank": 0.2, "score": 6102 }
      ,{ "datetime": "1900-01-03 00:17:08", "days": 2, "rank": 0.06, "score": 6086 }
      ,{ "datetime": "1900-01-02 22:11:38", "days": 2, "rank": 0.27, "score": 6075 }
      ,{ "datetime": "1900-01-03 00:03:02", "days": 2, "rank": 0.37, "score": 6009 }
      ,{ "datetime": "1900-01-02 14:00:06", "days": 2, "rank": 0, "score": 5985 }
      ,{ "datetime": "1900-01-02 22:00:51", "days": 2, "rank": 0.26, "score": 5972 }
      ,{ "datetime": "1900-01-02 15:52:53", "days": 2, "rank": 0.09, "score": 5954 }
      ,{ "datetime": "1900-01-02 20:43:27", "days": 2, "rank": 0.21, "score": 5944 }
      ,{ "datetime": "1900-01-02 20:01:21", "days": 2, "rank": 0.18, "score": 5940 }
      ,{ "datetime": "1900-01-02 16:55:08", "days": 2, "rank": 0.06, "score": 5938 }
      ,{ "datetime": "1900-01-02 16:59:28", "days": 2, "rank": 0.12, "score": 5925 }
      ,{ "datetime": "1900-01-02 20:09:24", "days": 2, "rank": 0.2, "score": 5907 }
      ,{ "datetime": "1900-01-02 12:00:00", "days": 2, "rank": 0, "score": 5848 }
      ,{ "datetime": "1900-01-02 12:44:57", "days": 2, "rank": 0.01, "score": 5797 }
      ,{ "datetime": "1900-01-02 19:46:43", "days": 2, "rank": 0.17, "score": 5795 }
      ,{ "datetime": "1900-01-03 01:50:26", "days": 2, "rank": 0.48, "score": 5793 }
      ,{ "datetime": "1900-01-02 19:06:02", "days": 2, "rank": 0.18, "score": 5788 }
      ,{ "datetime": "1900-01-03 01:13:49", "days": 2, "rank": 0.52, "score": 5608 }
      ,{ "datetime": "1900-01-02 22:47:23", "days": 2, "rank": 0.38, "score": 5578 }
      ,{ "datetime": "1900-01-02 23:26:53", "days": 2, "rank": 0.46, "score": 5465 }
      ,{ "datetime": "1900-01-02 21:39:15", "days": 2, "rank": 0.34, "score": 5442 }
      ,{ "datetime": "1900-01-02 19:58:17", "days": 2, "rank": 0.26, "score": 5395 }
      ,{ "datetime": "1900-01-03 00:11:48", "days": 2, "rank": 0.51, "score": 5342 }
      ,{ "datetime": "1900-01-02 23:14:50", "days": 2, "rank": 0.46, "score": 5302 }
      ,{ "datetime": "1900-01-02 21:43:36", "days": 2, "rank": 0.39, "score": 5221 }
      ,{ "datetime": "1900-01-03 00:38:20", "days": 2, "rank": 0.6, "score": 5221 }
      ,{ "datetime": "1900-01-02 20:15:56", "days": 2, "rank": 0.29, "score": 5190 }
      ,{ "datetime": "1900-01-02 12:00:00", "days": 2, "rank": 0, "score": 5185 }
      ,{ "datetime": "1900-01-02 23:50:02", "days": 2, "rank": 0.55, "score": 5172 }
      ,{ "datetime": "1900-01-03 01:08:40", "days": 2, "rank": 0.64, "score": 5156 }
      ,{ "datetime": "1900-01-02 22:09:28", "days": 2, "rank": 0.42, "score": 5142 }
      ,{ "datetime": "1900-01-02 16:34:50", "days": 2, "rank": 0.16, "score": 5126 }
      ,{ "datetime": "1900-01-02 21:52:14", "days": 2, "rank": 0.4, "score": 5126 }
      ,{ "datetime": "1900-01-02 13:33:57", "days": 2, "rank": 0.05, "score": 5122 }
      ,{ "datetime": "1900-01-02 18:03:08", "days": 2, "rank": 0.2, "score": 5121 }
      ,{ "datetime": "1900-01-02 16:36:10", "days": 2, "rank": 0.16, "score": 5117 }
      ,{ "datetime": "1900-01-03 00:29:59", "days": 2, "rank": 0.62, "score": 5030 }
      ,{ "datetime": "1900-01-02 16:30:54", "days": 2, "rank": 0.18, "score": 4934 }
      ,{ "datetime": "1900-01-02 17:42:18", "days": 2, "rank": 0.22, "score": 4884 }
      ,{ "datetime": "1900-01-03 02:15:18", "days": 2, "rank": 0.77, "score": 4882 }
      ,{ "datetime": "1900-01-03 00:55:15", "days": 2, "rank": 0.73, "score": 4840 }
      ,{ "datetime": "1900-01-02 12:43:06", "days": 2, "rank": 0, "score": 4815 }
      ,{ "datetime": "1900-01-02 21:14:34", "days": 2, "rank": 0.44, "score": 4663 }
      ,{ "datetime": "1900-01-02 15:51:32", "days": 2, "rank": 0.14, "score": 4494 }
      ,{ "datetime": "1900-01-02 18:56:04", "days": 2, "rank": 0.36, "score": 4082 }
      ,{ "datetime": "1900-01-02 23:31:38", "days": 2, "rank": 0.87, "score": 4034 }
      ,{ "datetime": "1900-01-03 00:23:26", "days": 2, "rank": 1.03, "score": 3829 }
      ,{ "datetime": "1900-01-02 22:24:28", "days": 2, "rank": 0.92, "score": 3533 }
      ,{ "datetime": "1900-01-02 13:08:12", "days": 2, "rank": 0.06, "score": 3471 }
      ,{ "datetime": "1900-01-02 16:20:31", "days": 2, "rank": 0.27, "score": 3376 }
      ,{ "datetime": "1900-01-02 19:28:12", "days": 2, "rank": 0.55, "score": 3369 }
      ,{ "datetime": "1900-01-03 00:45:54", "days": 2, "rank": 0.6, "score": 3266 }
      ,{ "datetime": "1900-01-02 12:24:43", "days": 2, "rank": 0, "score": 3252 }
      ,{ "datetime": "1900-01-02 23:19:41", "days": 2, "rank": 1.3, "score": 3095 }
      ,{ "datetime": "1900-01-03 01:26:02", "days": 2, "rank": 1.65, "score": 3013 }
      ,{ "datetime": "1900-01-03 04:54:09", "days": 2, "rank": 1.82, "score": 3013 }
      ,{ "datetime": "1900-01-03 02:02:54", "days": 2, "rank": 1.96, "score": 2753 }
      ,{ "datetime": "1900-01-02 18:35:38", "days": 2, "rank": 0.72, "score": 2612 }
      ,{ "datetime": "1900-01-03 04:59:47", "days": 2, "rank": 2.31, "score": 2540 }
      ,{ "datetime": "1900-01-02 12:41:51", "days": 2, "rank": 0.04, "score": 2484 }
      ,{ "datetime": "1900-01-02 14:36:49", "days": 2, "rank": 0.15, "score": 2456 }
      ,{ "datetime": "1900-01-02 20:08:04", "days": 2, "rank": 1.02, "score": 2397 }
      ,{ "datetime": "1900-01-02 18:30:18", "days": 2, "rank": 0.79, "score": 2390 }
      ,{ "datetime": "1900-01-02 12:00:00", "days": 2, "rank": 0, "score": 2337 }
      ,{ "datetime": "1900-01-02 15:19:12", "days": 2, "rank": 0.09, "score": 2327 }
      ,{ "datetime": "1900-01-02 21:16:34", "days": 2, "rank": 1.41, "score": 2288 }
      ,{ "datetime": "1900-01-02 21:16:48", "days": 2, "rank": 1.44, "score": 2271 }
      ,{ "datetime": "1900-01-02 21:00:08", "days": 2, "rank": 1.34, "score": 2267 }
      ,{ "datetime": "1900-01-02 20:31:57", "days": 2, "rank": 1.27, "score": 2206 }
      ,{ "datetime": "1900-01-02 16:31:33", "days": 2, "rank": 0.59, "score": 2204 }
      ,{ "datetime": "1900-01-02 19:38:18", "days": 2, "rank": 0.43, "score": 2120 }
      ,{ "datetime": "1900-01-02 20:01:47", "days": 2, "rank": 1.26, "score": 2073 }
      ,{ "datetime": "1900-01-02 20:58:52", "days": 2, "rank": 1.8, "score": 1779 }
      ,{ "datetime": "1900-01-03 02:16:46", "days": 2, "rank": 2.66, "score": 1716 }
      ,{ "datetime": "1900-01-02 23:15:26", "days": 2, "rank": 3.01, "score": 1599 }
      ,{ "datetime": "1900-01-03 02:32:26", "days": 2, "rank": 4.01, "score": 1499 }
      ,{ "datetime": "1900-01-02 19:15:42", "days": 2, "rank": 1.42, "score": 1484 }
      ,{ "datetime": "1900-01-02 14:04:19", "days": 2, "rank": 0.2, "score": 1098 }
      ,{ "datetime": "1900-01-02 22:22:56", "days": 2, "rank": 0.37, "score": 1098 }
      ,{ "datetime": "1900-01-02 20:28:39", "days": 2, "rank": 2.58, "score": 1084 }
      ,{ "datetime": "1900-01-02 12:22:26", "days": 2, "rank": 0.02, "score": 1014 }
      ,{ "datetime": "1900-01-02 13:00:54", "days": 2, "rank": 0.3, "score": 989 }
      ,{ "datetime": "1900-01-02 12:00:00", "days": 2, "rank": 0, "score": 953 }
      ,{ "datetime": "1900-01-04 00:17:24", "days": 3, "rank": 0, "score": 12688 }
      ,{ "datetime": "1900-01-03 08:01:07", "days": 3, "rank": 0.02, "score": 10440 }
      ,{ "datetime": "1900-01-04 01:26:16", "days": 3, "rank": 0.02, "score": 10106 }
      ,{ "datetime": "1900-01-03 21:21:30", "days": 3, "rank": 0.02, "score": 10082 }
      ,{ "datetime": "1900-01-03 23:02:28", "days": 3, "rank": 0.03, "score": 9820 }
      ,{ "datetime": "1900-01-04 01:00:15", "days": 3, "rank": 0.04, "score": 9708 }
      ,{ "datetime": "1900-01-03 10:32:54", "days": 3, "rank": 0.03, "score": 9601 }
      ,{ "datetime": "1900-01-04 02:19:06", "days": 3, "rank": 0.04, "score": 9580 }
      ,{ "datetime": "1900-01-03 23:22:20", "days": 3, "rank": 0.05, "score": 9227 }
      ,{ "datetime": "1900-01-03 15:47:44", "days": 3, "rank": 0.04, "score": 9106 }
      ,{ "datetime": "1900-01-03 05:03:12", "days": 3, "rank": 0.04, "score": 9008 }
      ,{ "datetime": "1900-01-04 03:35:11", "days": 3, "rank": 0.05, "score": 8950 }
      ,{ "datetime": "1900-01-03 17:02:47", "days": 3, "rank": 0.05, "score": 8914 }
      ,{ "datetime": "1900-01-03 14:22:26", "days": 3, "rank": 0.05, "score": 8793 }
      ,{ "datetime": "1900-01-04 01:42:17", "days": 3, "rank": 0.06, "score": 8764 }
      ,{ "datetime": "1900-01-04 01:43:49", "days": 3, "rank": 0.06, "score": 8725 }
      ,{ "datetime": "1900-01-03 17:07:47", "days": 3, "rank": 0.06, "score": 8502 }
      ,{ "datetime": "1900-01-03 09:45:40", "days": 3, "rank": 0.05, "score": 8444 }
      ,{ "datetime": "1900-01-03 11:09:00", "days": 3, "rank": 0.06, "score": 8431 }
      ,{ "datetime": "1900-01-03 14:04:13", "days": 3, "rank": 0.07, "score": 8219 }
      ,{ "datetime": "1900-01-03 23:51:09", "days": 3, "rank": 0.1, "score": 8038 }
      ,{ "datetime": "1900-01-04 00:15:11", "days": 3, "rank": 0.1, "score": 8007 }
      ,{ "datetime": "1900-01-03 15:19:34", "days": 3, "rank": 0.09, "score": 7996 }
      ,{ "datetime": "1900-01-03 19:57:27", "days": 3, "rank": 0.11, "score": 7843 }
      ,{ "datetime": "1900-01-03 15:55:26", "days": 3, "rank": 0.11, "score": 7733 }
      ,{ "datetime": "1900-01-03 18:12:22", "days": 3, "rank": 0.11, "score": 7731 }
      ,{ "datetime": "1900-01-03 22:10:21", "days": 3, "rank": 0.12, "score": 7723 }
      ,{ "datetime": "1900-01-04 02:30:09", "days": 3, "rank": 0.15, "score": 7684 }
      ,{ "datetime": "1900-01-03 21:58:31", "days": 3, "rank": 0.15, "score": 7528 }
      ,{ "datetime": "1900-01-04 04:19:00", "days": 3, "rank": 0.21, "score": 7355 }
      ,{ "datetime": "1900-01-04 01:33:17", "days": 3, "rank": 0.2, "score": 7354 }
      ,{ "datetime": "1900-01-03 21:08:56", "days": 3, "rank": 0.19, "score": 7246 }
      ,{ "datetime": "1900-01-03 22:11:53", "days": 3, "rank": 0.2, "score": 7235 }
      ,{ "datetime": "1900-01-03 23:26:42", "days": 3, "rank": 0.23, "score": 7130 }
      ,{ "datetime": "1900-01-03 22:04:18", "days": 3, "rank": 0.22, "score": 7115 }
      ,{ "datetime": "1900-01-04 01:45:00", "days": 3, "rank": 0.26, "score": 7092 }
      ,{ "datetime": "1900-01-03 15:38:33", "days": 3, "rank": 0.22, "score": 6967 }
      ,{ "datetime": "1900-01-03 23:48:14", "days": 3, "rank": 0.31, "score": 6834 }
      ,{ "datetime": "1900-01-03 22:04:07", "days": 3, "rank": 0.3, "score": 6792 }
      ,{ "datetime": "1900-01-04 01:56:21", "days": 3, "rank": 0.35, "score": 6763 }
      ,{ "datetime": "1900-01-04 00:37:48", "days": 3, "rank": 0.35, "score": 6730 }
      ,{ "datetime": "1900-01-03 11:17:53", "days": 3, "rank": 0.25, "score": 6717 }
      ,{ "datetime": "1900-01-03 17:32:17", "days": 3, "rank": 0.3, "score": 6629 }
      ,{ "datetime": "1900-01-03 23:22:54", "days": 3, "rank": 0.39, "score": 6572 }
      ,{ "datetime": "1900-01-03 23:27:25", "days": 3, "rank": 0.42, "score": 6495 }
      ,{ "datetime": "1900-01-04 00:11:15", "days": 3, "rank": 0.46, "score": 6418 }
      ,{ "datetime": "1900-01-03 21:13:17", "days": 3, "rank": 0.42, "score": 6383 }
      ,{ "datetime": "1900-01-04 02:07:00", "days": 3, "rank": 0.5, "score": 6381 }
      ,{ "datetime": "1900-01-03 23:51:59", "days": 3, "rank": 0.48, "score": 6342 }
      ,{ "datetime": "1900-01-03 22:55:04", "days": 3, "rank": 0.49, "score": 6289 }
      ,{ "datetime": "1900-01-03 22:55:02", "days": 3, "rank": 0.51, "score": 6226 }
      ,{ "datetime": "1900-01-03 19:58:51", "days": 3, "rank": 0.48, "score": 6195 }
      ,{ "datetime": "1900-01-03 22:07:19", "days": 3, "rank": 0.53, "score": 6162 }
      ,{ "datetime": "1900-01-03 22:13:54", "days": 3, "rank": 0.54, "score": 6140 }
      ,{ "datetime": "1900-01-03 12:05:33", "days": 3, "rank": 0.43, "score": 6130 }
      ,{ "datetime": "1900-01-03 23:53:43", "days": 3, "rank": 0.58, "score": 6106 }
      ,{ "datetime": "1900-01-03 18:42:00", "days": 3, "rank": 0.5, "score": 6102 }
      ,{ "datetime": "1900-01-04 00:01:56", "days": 3, "rank": 0.61, "score": 6100 }
      ,{ "datetime": "1900-01-03 20:08:56", "days": 3, "rank": 0.53, "score": 6074 }
      ,{ "datetime": "1900-01-03 19:07:53", "days": 3, "rank": 0.51, "score": 6019 }
      ,{ "datetime": "1900-01-03 21:05:28", "days": 3, "rank": 0.57, "score": 6018 }
      ,{ "datetime": "1900-01-03 23:30:04", "days": 3, "rank": 0.63, "score": 6017 }
      ,{ "datetime": "1900-01-04 01:30:33", "days": 3, "rank": 0.69, "score": 5996 }
      ,{ "datetime": "1900-01-03 22:39:31", "days": 3, "rank": 0.63, "score": 5944 }
      ,{ "datetime": "1900-01-03 15:53:58", "days": 3, "rank": 0.54, "score": 5895 }
      ,{ "datetime": "1900-01-03 19:56:51", "days": 3, "rank": 0.6, "score": 5875 }
      ,{ "datetime": "1900-01-03 21:59:22", "days": 3, "rank": 0.65, "score": 5847 }
      ,{ "datetime": "1900-01-03 22:40:50", "days": 3, "rank": 0.71, "score": 5773 }
      ,{ "datetime": "1900-01-03 19:03:45", "days": 3, "rank": 0.58, "score": 5743 }
      ,{ "datetime": "1900-01-03 22:16:49", "days": 3, "rank": 0.73, "score": 5673 }
      ,{ "datetime": "1900-01-03 21:36:02", "days": 3, "rank": 0.72, "score": 5655 }
      ,{ "datetime": "1900-01-04 02:45:49", "days": 3, "rank": 0.88, "score": 5654 }
      ,{ "datetime": "1900-01-03 23:11:14", "days": 3, "rank": 0.79, "score": 5605 }
      ,{ "datetime": "1900-01-03 21:58:31", "days": 3, "rank": 0.8, "score": 5484 }
      ,{ "datetime": "1900-01-04 00:02:33", "days": 3, "rank": 0.91, "score": 5440 }
      ,{ "datetime": "1900-01-03 12:19:38", "days": 3, "rank": 0.68, "score": 5397 }
      ,{ "datetime": "1900-01-03 19:42:09", "days": 3, "rank": 0.78, "score": 5388 }
      ,{ "datetime": "1900-01-03 17:22:40", "days": 3, "rank": 0.7, "score": 5381 }
      ,{ "datetime": "1900-01-03 12:34:19", "days": 3, "rank": 0.74, "score": 5220 }
      ,{ "datetime": "1900-01-03 17:19:25", "days": 3, "rank": 0.85, "score": 5089 }
      ,{ "datetime": "1900-01-03 13:15:18", "days": 3, "rank": 0.81, "score": 5045 }
      ,{ "datetime": "1900-01-03 23:56:27", "days": 3, "rank": 1.16, "score": 4846 }
      ,{ "datetime": "1900-01-03 21:57:38", "days": 3, "rank": 1.08, "score": 4814 }
      ,{ "datetime": "1900-01-03 19:19:44", "days": 3, "rank": 1.02, "score": 4755 }
      ,{ "datetime": "1900-01-03 18:42:07", "days": 3, "rank": 1.01, "score": 4729 }
      ,{ "datetime": "1900-01-03 10:54:55", "days": 3, "rank": 0.98, "score": 4456 }
      ,{ "datetime": "1900-01-03 06:04:35", "days": 3, "rank": 0.96, "score": 4446 }
      ,{ "datetime": "1900-01-03 11:38:35", "days": 3, "rank": 1.05, "score": 4318 }
      ,{ "datetime": "1900-01-04 02:19:46", "days": 3, "rank": 1.6, "score": 4214 }
      ,{ "datetime": "1900-01-04 00:30:36", "days": 3, "rank": 1.53, "score": 4153 }
      ,{ "datetime": "1900-01-03 10:13:52", "days": 3, "rank": 1.2, "score": 3983 }
      ,{ "datetime": "1900-01-03 13:40:14", "days": 3, "rank": 1.28, "score": 3939 }
      ,{ "datetime": "1900-01-03 22:02:10", "days": 3, "rank": 1.62, "score": 3847 }
      ,{ "datetime": "1900-01-03 20:27:42", "days": 3, "rank": 1.53, "score": 3841 }
      ,{ "datetime": "1900-01-03 11:53:05", "days": 3, "rank": 1.3, "score": 3840 }
      ,{ "datetime": "1900-01-03 23:16:52", "days": 3, "rank": 1.75, "score": 3796 }
      ,{ "datetime": "1900-01-03 20:12:47", "days": 3, "rank": 1.57, "score": 3764 }
      ,{ "datetime": "1900-01-04 01:21:31", "days": 3, "rank": 2.06, "score": 3596 }
      ,{ "datetime": "1900-01-04 00:25:47", "days": 3, "rank": 2.11, "score": 3483 }
      ,{ "datetime": "1900-01-03 20:54:55", "days": 3, "rank": 1.97, "score": 3316 }
      ,{ "datetime": "1900-01-03 16:48:38", "days": 3, "rank": 1.88, "score": 3158 }
      ,{ "datetime": "1900-01-03 21:47:42", "days": 3, "rank": 2.23, "score": 3108 }
      ,{ "datetime": "1900-01-04 01:51:04", "days": 3, "rank": 2.69, "score": 3073 }
      ,{ "datetime": "1900-01-04 02:42:52", "days": 3, "rank": 2.9, "score": 2954 }
      ,{ "datetime": "1900-01-03 22:26:55", "days": 3, "rank": 3.03, "score": 2603 }
      ,{ "datetime": "1900-01-04 02:11:26", "days": 3, "rank": 3.61, "score": 2505 }
      ,{ "datetime": "1900-01-03 14:04:58", "days": 3, "rank": 3.21, "score": 2131 }
      ,{ "datetime": "1900-01-03 22:16:34", "days": 3, "rank": 3.81, "score": 2111 }
      ,{ "datetime": "1900-01-03 22:04:27", "days": 3, "rank": 4.32, "score": 1915 }
      ,{ "datetime": "1900-01-03 21:30:50", "days": 3, "rank": 4.31, "score": 1890 }
      ,{ "datetime": "1900-01-03 14:19:58", "days": 3, "rank": 3.84, "score": 1829 }
      ,{ "datetime": "1900-01-03 10:09:51", "days": 3, "rank": 2.82, "score": 1702 }
      ,{ "datetime": "1900-01-03 23:50:19", "days": 3, "rank": 5.63, "score": 1603 }
      ,{ "datetime": "1900-01-03 08:42:23", "days": 3, "rank": 3.99, "score": 1602 }
      ,{ "datetime": "1900-01-03 19:05:10", "days": 3, "rank": 4.86, "score": 1571 }
      ,{ "datetime": "1900-01-03 19:04:39", "days": 3, "rank": 5.14, "score": 1482 }
      ,{ "datetime": "1900-01-03 19:14:07", "days": 3, "rank": 5.49, "score": 1387 }
      ,{ "datetime": "1900-01-03 18:22:25", "days": 3, "rank": 5.56, "score": 1339 }
      ,{ "datetime": "1900-01-03 23:13:07", "days": 3, "rank": 7.5, "score": 1061 }
      ,{ "datetime": "1900-01-03 19:24:40", "days": 3, "rank": 7.03, "score": 1020 }
      ,{ "datetime": "1900-01-03 18:43:00", "days": 3, "rank": 15.63, "score": 4 }
      ,{ "datetime": "1900-01-04 22:56:25", "days": 4, "rank": 0, "score": 12986 }
      ,{ "datetime": "1900-01-05 00:18:32", "days": 4, "rank": 0, "score": 12263 }
      ,{ "datetime": "1900-01-04 17:10:15", "days": 4, "rank": 0, "score": 12234 }
      ,{ "datetime": "1900-01-04 23:16:09", "days": 4, "rank": 0.02, "score": 11005 }
      ,{ "datetime": "1900-01-04 14:55:03", "days": 4, "rank": 0.02, "score": 10698 }
      ,{ "datetime": "1900-01-04 23:19:54", "days": 4, "rank": 0.03, "score": 10391 }
      ,{ "datetime": "1900-01-04 21:56:06", "days": 4, "rank": 0.03, "score": 10212 }
      ,{ "datetime": "1900-01-04 19:16:08", "days": 4, "rank": 0.03, "score": 10206 }
      ,{ "datetime": "1900-01-04 08:26:50", "days": 4, "rank": 0.03, "score": 10151 }
      ,{ "datetime": "1900-01-04 20:11:00", "days": 4, "rank": 0.03, "score": 10148 }
      ,{ "datetime": "1900-01-04 23:41:05", "days": 4, "rank": 0.04, "score": 9925 }
      ,{ "datetime": "1900-01-04 17:24:29", "days": 4, "rank": 0.04, "score": 9835 }
      ,{ "datetime": "1900-01-05 00:11:51", "days": 4, "rank": 0.06, "score": 9363 }
      ,{ "datetime": "1900-01-05 03:23:08", "days": 4, "rank": 0.05, "score": 9293 }
      ,{ "datetime": "1900-01-04 06:20:01", "days": 4, "rank": 0.06, "score": 9186 }
      ,{ "datetime": "1900-01-05 01:43:05", "days": 4, "rank": 0.06, "score": 9118 }
      ,{ "datetime": "1900-01-04 19:29:21", "days": 4, "rank": 0.05, "score": 9109 }
      ,{ "datetime": "1900-01-04 17:22:43", "days": 4, "rank": 0.06, "score": 9000 }
      ,{ "datetime": "1900-01-05 03:54:24", "days": 4, "rank": 0.09, "score": 8679 }
      ,{ "datetime": "1900-01-05 00:09:37", "days": 4, "rank": 0.09, "score": 8506 }
      ,{ "datetime": "1900-01-04 23:18:35", "days": 4, "rank": 0.09, "score": 8491 }
      ,{ "datetime": "1900-01-05 02:20:52", "days": 4, "rank": 0.11, "score": 8333 }
      ,{ "datetime": "1900-01-04 23:07:42", "days": 4, "rank": 0.1, "score": 8299 }
      ,{ "datetime": "1900-01-04 12:38:16", "days": 4, "rank": 0.09, "score": 8231 }
      ,{ "datetime": "1900-01-05 02:03:38", "days": 4, "rank": 0.12, "score": 8214 }
      ,{ "datetime": "1900-01-05 00:07:43", "days": 4, "rank": 0.12, "score": 8148 }
      ,{ "datetime": "1900-01-04 19:08:08", "days": 4, "rank": 0.11, "score": 8113 }
      ,{ "datetime": "1900-01-04 14:40:58", "days": 4, "rank": 0.15, "score": 7784 }
      ,{ "datetime": "1900-01-05 00:31:55", "days": 4, "rank": 0.18, "score": 7776 }
      ,{ "datetime": "1900-01-04 20:27:48", "days": 4, "rank": 0.16, "score": 7748 }
      ,{ "datetime": "1900-01-05 01:37:03", "days": 4, "rank": 0.2, "score": 7738 }
      ,{ "datetime": "1900-01-04 19:53:50", "days": 4, "rank": 0.22, "score": 7494 }
      ,{ "datetime": "1900-01-04 23:38:41", "days": 4, "rank": 0.24, "score": 7477 }
      ,{ "datetime": "1900-01-04 18:50:41", "days": 4, "rank": 0.23, "score": 7397 }
      ,{ "datetime": "1900-01-04 21:08:56", "days": 4, "rank": 0.26, "score": 7324 }
      ,{ "datetime": "1900-01-04 21:57:52", "days": 4, "rank": 0.26, "score": 7324 }
      ,{ "datetime": "1900-01-04 19:02:31", "days": 4, "rank": 0.25, "score": 7320 }
      ,{ "datetime": "1900-01-04 16:41:10", "days": 4, "rank": 0.24, "score": 7312 }
      ,{ "datetime": "1900-01-04 15:59:30", "days": 4, "rank": 0.22, "score": 7299 }
      ,{ "datetime": "1900-01-05 01:59:13", "days": 4, "rank": 0.31, "score": 7248 }
      ,{ "datetime": "1900-01-05 01:50:50", "days": 4, "rank": 0.33, "score": 7243 }
      ,{ "datetime": "1900-01-04 22:19:39", "days": 4, "rank": 0.3, "score": 7216 }
      ,{ "datetime": "1900-01-04 23:21:43", "days": 4, "rank": 0.33, "score": 7136 }
      ,{ "datetime": "1900-01-04 23:56:54", "days": 4, "rank": 0.38, "score": 7028 }
      ,{ "datetime": "1900-01-04 23:39:35", "days": 4, "rank": 0.38, "score": 7020 }
      ,{ "datetime": "1900-01-05 04:09:55", "days": 4, "rank": 0.44, "score": 7006 }
      ,{ "datetime": "1900-01-04 22:15:52", "days": 4, "rank": 0.37, "score": 6991 }
      ,{ "datetime": "1900-01-04 23:36:42", "days": 4, "rank": 0.42, "score": 6854 }
      ,{ "datetime": "1900-01-04 10:35:05", "days": 4, "rank": 0.34, "score": 6852 }
      ,{ "datetime": "1900-01-04 21:28:56", "days": 4, "rank": 0.43, "score": 6826 }
      ,{ "datetime": "1900-01-04 10:31:15", "days": 4, "rank": 0.35, "score": 6812 }
      ,{ "datetime": "1900-01-04 16:00:44", "days": 4, "rank": 0.4, "score": 6756 }
      ,{ "datetime": "1900-01-04 13:00:44", "days": 4, "rank": 0.4, "score": 6713 }
      ,{ "datetime": "1900-01-05 01:19:39", "days": 4, "rank": 0.54, "score": 6702 }
      ,{ "datetime": "1900-01-04 15:20:45", "days": 4, "rank": 0.42, "score": 6685 }
      ,{ "datetime": "1900-01-04 20:58:59", "days": 4, "rank": 0.49, "score": 6651 }
      ,{ "datetime": "1900-01-05 01:03:52", "days": 4, "rank": 0.6, "score": 6582 }
      ,{ "datetime": "1900-01-04 23:22:16", "days": 4, "rank": 0.62, "score": 6493 }
      ,{ "datetime": "1900-01-04 17:59:50", "days": 4, "rank": 0.55, "score": 6444 }
      ,{ "datetime": "1900-01-04 21:49:59", "days": 4, "rank": 0.61, "score": 6422 }
      ,{ "datetime": "1900-01-04 17:46:49", "days": 4, "rank": 0.61, "score": 6330 }
      ,{ "datetime": "1900-01-04 22:17:38", "days": 4, "rank": 0.69, "score": 6322 }
      ,{ "datetime": "1900-01-04 20:53:30", "days": 4, "rank": 0.66, "score": 6306 }
      ,{ "datetime": "1900-01-04 05:11:37", "days": 4, "rank": 0.56, "score": 6303 }
      ,{ "datetime": "1900-01-04 22:43:01", "days": 4, "rank": 0.73, "score": 6255 }
      ,{ "datetime": "1900-01-04 19:16:00", "days": 4, "rank": 0.71, "score": 6185 }
      ,{ "datetime": "1900-01-04 20:28:33", "days": 4, "rank": 0.75, "score": 6155 }
      ,{ "datetime": "1900-01-04 23:25:20", "days": 4, "rank": 0.82, "score": 6155 }
      ,{ "datetime": "1900-01-04 12:24:39", "days": 4, "rank": 0.66, "score": 6151 }
      ,{ "datetime": "1900-01-05 03:05:30", "days": 4, "rank": 0.93, "score": 6139 }
      ,{ "datetime": "1900-01-05 03:12:42", "days": 4, "rank": 0.94, "score": 6129 }
      ,{ "datetime": "1900-01-04 21:18:39", "days": 4, "rank": 0.79, "score": 6128 }
      ,{ "datetime": "1900-01-05 02:19:58", "days": 4, "rank": 0.95, "score": 6102 }
      ,{ "datetime": "1900-01-04 21:57:08", "days": 4, "rank": 0.83, "score": 6089 }
      ,{ "datetime": "1900-01-05 03:24:26", "days": 4, "rank": 1, "score": 6062 }
      ,{ "datetime": "1900-01-04 22:42:02", "days": 4, "rank": 0.88, "score": 6050 }
      ,{ "datetime": "1900-01-05 01:24:11", "days": 4, "rank": 1.01, "score": 5987 }
      ,{ "datetime": "1900-01-04 22:45:38", "days": 4, "rank": 0.93, "score": 5972 }
      ,{ "datetime": "1900-01-04 08:28:44", "days": 4, "rank": 0.75, "score": 5948 }
      ,{ "datetime": "1900-01-04 21:42:10", "days": 4, "rank": 0.91, "score": 5946 }
      ,{ "datetime": "1900-01-04 11:34:55", "days": 4, "rank": 0.77, "score": 5930 }
      ,{ "datetime": "1900-01-05 03:22:07", "days": 4, "rank": 1.11, "score": 5923 }
      ,{ "datetime": "1900-01-05 01:55:32", "days": 4, "rank": 1.08, "score": 5911 }
      ,{ "datetime": "1900-01-05 02:11:43", "days": 4, "rank": 1.11, "score": 5877 }
      ,{ "datetime": "1900-01-04 20:01:23", "days": 4, "rank": 0.93, "score": 5849 }
      ,{ "datetime": "1900-01-04 12:57:50", "days": 4, "rank": 0.85, "score": 5809 }
      ,{ "datetime": "1900-01-04 18:39:51", "days": 4, "rank": 1, "score": 5688 }
      ,{ "datetime": "1900-01-04 23:36:19", "days": 4, "rank": 1.19, "score": 5623 }
      ,{ "datetime": "1900-01-04 16:24:59", "days": 4, "rank": 1.06, "score": 5511 }
      ,{ "datetime": "1900-01-05 00:16:11", "days": 4, "rank": 1.21, "score": 5483 }
      ,{ "datetime": "1900-01-05 03:36:29", "days": 4, "rank": 1.35, "score": 5469 }
      ,{ "datetime": "1900-01-05 00:34:03", "days": 4, "rank": 1.32, "score": 5468 }
      ,{ "datetime": "1900-01-04 18:10:29", "days": 4, "rank": 1.12, "score": 5462 }
      ,{ "datetime": "1900-01-04 22:23:06", "days": 4, "rank": 1.24, "score": 5462 }
      ,{ "datetime": "1900-01-04 18:19:56", "days": 4, "rank": 1.13, "score": 5459 }
      ,{ "datetime": "1900-01-04 14:58:24", "days": 4, "rank": 1.08, "score": 5436 }
      ,{ "datetime": "1900-01-04 21:53:21", "days": 4, "rank": 1.25, "score": 5416 }
      ,{ "datetime": "1900-01-04 08:26:57", "days": 4, "rank": 1.03, "score": 5415 }
      ,{ "datetime": "1900-01-04 20:05:40", "days": 4, "rank": 1.25, "score": 5325 }
      ,{ "datetime": "1900-01-04 20:01:41", "days": 4, "rank": 1.28, "score": 5260 }
      ,{ "datetime": "1900-01-04 10:25:13", "days": 4, "rank": 1.15, "score": 5196 }
      ,{ "datetime": "1900-01-04 17:06:34", "days": 4, "rank": 1.25, "score": 5179 }
      
      ,{ "datetime": "1900-01-04 05:50:42", "days": 4, "rank": 1.18, "score": 5089 }
      ,{ "datetime": "1900-01-04 19:38:54", "days": 4, "rank": 1.38, "score": 5065 }
      ,{ "datetime": "1900-01-05 00:58:30", "days": 4, "rank": 1.63, "score": 5050 }
      ,{ "datetime": "1900-01-04 23:52:39", "days": 4, "rank": 1.61, "score": 4989 }
      ,{ "datetime": "1900-01-05 01:42:34", "days": 4, "rank": 1.74, "score": 4913 }
      ,{ "datetime": "1900-01-04 20:24:27", "days": 4, "rank": 1.55, "score": 4797 }
      ,{ "datetime": "1900-01-04 05:24:25", "days": 4, "rank": 1.41, "score": 4628 }
      ,{ "datetime": "1900-01-04 15:12:37", "days": 4, "rank": 1.51, "score": 4626 }
      ,{ "datetime": "1900-01-05 01:23:24", "days": 4, "rank": 2.07, "score": 4463 }
      ,{ "datetime": "1900-01-04 20:21:56", "days": 4, "rank": 1.81, "score": 4380 }
      ,{ "datetime": "1900-01-04 11:14:08", "days": 4, "rank": 1.62, "score": 4324 }
      ,{ "datetime": "1900-01-05 04:26:42", "days": 4, "rank": 2.41, "score": 4214 }
      ,{ "datetime": "1900-01-05 02:33:31", "days": 4, "rank": 2.44, "score": 4103 }
      ,{ "datetime": "1900-01-04 19:38:16", "days": 4, "rank": 2.21, "score": 3872 }
      ,{ "datetime": "1900-01-04 18:34:32", "days": 4, "rank": 2.22, "score": 3819 }
      ,{ "datetime": "1900-01-04 15:26:09", "days": 4, "rank": 3, "score": 3748 }
      ,{ "datetime": "1900-01-05 03:05:23", "days": 4, "rank": 2.99, "score": 3654 }
      ,{ "datetime": "1900-01-04 23:13:12", "days": 4, "rank": 2.75, "score": 3613 }
      ,{ "datetime": "1900-01-04 20:57:38", "days": 4, "rank": 2.6, "score": 3568 }
      ,{ "datetime": "1900-01-05 00:11:14", "days": 4, "rank": 3, "score": 3494 }
      ,{ "datetime": "1900-01-04 18:55:31", "days": 4, "rank": 3.26, "score": 3016 }
      ,{ "datetime": "1900-01-04 11:10:11", "days": 4, "rank": 3.55, "score": 2642 }
      ,{ "datetime": "1900-01-04 20:19:00", "days": 4, "rank": 4.05, "score": 2617 }
      ,{ "datetime": "1900-01-05 00:05:48", "days": 4, "rank": 3.09, "score": 2596 }
      ,{ "datetime": "1900-01-04 08:50:38", "days": 4, "rank": 3.58, "score": 2375 }
      ,{ "datetime": "1900-01-04 11:55:59", "days": 4, "rank": 4.37, "score": 2256 }
      ,{ "datetime": "1900-01-05 00:50:31", "days": 4, "rank": 5.71, "score": 2209 }
      ,{ "datetime": "1900-01-04 06:42:47", "days": 4, "rank": 4.43, "score": 2149 }
      ,{ "datetime": "1900-01-04 14:20:36", "days": 4, "rank": 5.49, "score": 1890 }
      ,{ "datetime": "1900-01-05 00:46:05", "days": 4, "rank": 8.69, "score": 1439 }
      ,{ "datetime": "1900-01-04 07:57:37", "days": 4, "rank": 6.94, "score": 1414 }
      ,{ "datetime": "1900-01-04 23:32:53", "days": 4, "rank": 8.93, "score": 1341 }
      ,{ "datetime": "1900-01-05 01:02:33", "days": 4, "rank": 8.85, "score": 1292 }
      ,{ "datetime": "1900-01-05 01:08:18", "days": 4, "rank": 10.82, "score": 1098 }
      ,{ "datetime": "1900-01-05 16:13:29", "days": 5, "rank": 0, "score": 13771 }
      ,{ "datetime": "1900-01-06 01:31:25", "days": 5, "rank": 0, "score": 13757 }
      ,{ "datetime": "1900-01-05 16:11:09", "days": 5, "rank": 0, "score": 13279 }
      ,{ "datetime": "1900-01-05 16:34:06", "days": 5, "rank": 0, "score": 12991 }
      ,{ "datetime": "1900-01-05 16:23:50", "days": 5, "rank": 0, "score": 12860 }
      ,{ "datetime": "1900-01-05 17:31:57", "days": 5, "rank": 0, "score": 12719 }
      ,{ "datetime": "1900-01-05 12:57:49", "days": 5, "rank": 0.01, "score": 11932 }
      ,{ "datetime": "1900-01-05 13:43:23", "days": 5, "rank": 0.01, "score": 11771 }
      ,{ "datetime": "1900-01-06 01:10:14", "days": 5, "rank": 0.02, "score": 11629 }
      ,{ "datetime": "1900-01-05 13:13:47", "days": 5, "rank": 0.01, "score": 11470 }
      ,{ "datetime": "1900-01-06 03:41:03", "days": 5, "rank": 0.03, "score": 11186 }
      ,{ "datetime": "1900-01-06 00:42:26", "days": 5, "rank": 0.03, "score": 11108 }
      ,{ "datetime": "1900-01-06 01:42:43", "days": 5, "rank": 0.03, "score": 11097 }
      ,{ "datetime": "1900-01-05 17:27:12", "days": 5, "rank": 0.02, "score": 11086 }
      ,{ "datetime": "1900-01-05 17:59:45", "days": 5, "rank": 0.02, "score": 10984 }
      ,{ "datetime": "1900-01-06 01:56:32", "days": 5, "rank": 0.03, "score": 10953 }
      ,{ "datetime": "1900-01-06 04:55:26", "days": 5, "rank": 0.04, "score": 10678 }
      ,{ "datetime": "1900-01-05 19:28:49", "days": 5, "rank": 0.03, "score": 10592 }
      ,{ "datetime": "1900-01-05 23:56:18", "days": 5, "rank": 0.04, "score": 10533 }
      ,{ "datetime": "1900-01-06 02:06:34", "days": 5, "rank": 0.04, "score": 10526 }
      ,{ "datetime": "1900-01-06 04:28:44", "days": 5, "rank": 0.05, "score": 10524 }
      ,{ "datetime": "1900-01-06 01:12:33", "days": 5, "rank": 0.04, "score": 10499 }
      ,{ "datetime": "1900-01-05 22:14:52", "days": 5, "rank": 0.04, "score": 10481 }
      ,{ "datetime": "1900-01-05 21:34:03", "days": 5, "rank": 0.04, "score": 10471 }
      ,{ "datetime": "1900-01-05 12:46:58", "days": 5, "rank": 0.03, "score": 10426 }
      ,{ "datetime": "1900-01-05 17:24:07", "days": 5, "rank": 0.03, "score": 10426 }
      ,{ "datetime": "1900-01-06 00:56:45", "days": 5, "rank": 0.05, "score": 10412 }
      ,{ "datetime": "1900-01-05 17:46:44", "days": 5, "rank": 0.04, "score": 10331 }
      ,{ "datetime": "1900-01-05 21:43:01", "days": 5, "rank": 0.05, "score": 10327 }
      ,{ "datetime": "1900-01-05 15:17:42", "days": 5, "rank": 0.04, "score": 10276 }
      ,{ "datetime": "1900-01-06 04:43:38", "days": 5, "rank": 0.05, "score": 10232 }
      ,{ "datetime": "1900-01-06 03:34:09", "days": 5, "rank": 0.06, "score": 10232 }
      ,{ "datetime": "1900-01-05 07:35:59", "days": 5, "rank": 0.03, "score": 10212 }
      ,{ "datetime": "1900-01-05 14:15:07", "days": 5, "rank": 0.04, "score": 10212 }
      ,{ "datetime": "1900-01-06 00:27:18", "days": 5, "rank": 0.06, "score": 10145 }
      ,{ "datetime": "1900-01-05 22:23:30", "days": 5, "rank": 0.06, "score": 10094 }
      ,{ "datetime": "1900-01-06 02:55:23", "days": 5, "rank": 0.05, "score": 10050 }
      ,{ "datetime": "1900-01-05 17:27:22", "days": 5, "rank": 0.05, "score": 10023 }
      ,{ "datetime": "1900-01-05 16:13:29", "days": 5, "rank": 0.06, "score": 9863 }
      ,{ "datetime": "1900-01-05 12:12:43", "days": 5, "rank": 0.05, "score": 9859 }
      ,{ "datetime": "1900-01-05 23:54:15", "days": 5, "rank": 0.06, "score": 9841 }
      ,{ "datetime": "1900-01-06 02:18:45", "days": 5, "rank": 0.06, "score": 9835 }
      ,{ "datetime": "1900-01-05 14:07:02", "days": 5, "rank": 0.06, "score": 9761 }
      ,{ "datetime": "1900-01-05 15:13:04", "days": 5, "rank": 0.06, "score": 9748 }
      ,{ "datetime": "1900-01-06 01:51:25", "days": 5, "rank": 0.06, "score": 9682 }
      ,{ "datetime": "1900-01-06 04:13:16", "days": 5, "rank": 0.07, "score": 9678 }
      ,{ "datetime": "1900-01-05 19:49:52", "days": 5, "rank": 0.06, "score": 9584 }
      ,{ "datetime": "1900-01-05 10:22:23", "days": 5, "rank": 0.05, "score": 9422 }
      ,{ "datetime": "1900-01-05 13:46:51", "days": 5, "rank": 0.05, "score": 9418 }
      ,{ "datetime": "1900-01-05 16:58:51", "days": 5, "rank": 0.06, "score": 9402 }
      ,{ "datetime": "1900-01-06 02:13:00", "days": 5, "rank": 0.08, "score": 9354 }
      ,{ "datetime": "1900-01-05 23:43:15", "days": 5, "rank": 0.07, "score": 9303 }
      ,{ "datetime": "1900-01-05 18:01:38", "days": 5, "rank": 0.06, "score": 9300 }
      ,{ "datetime": "1900-01-06 01:35:10", "days": 5, "rank": 0.09, "score": 9167 }
      ,{ "datetime": "1900-01-05 22:16:56", "days": 5, "rank": 0.08, "score": 9157 }
      ,{ "datetime": "1900-01-05 22:51:35", "days": 5, "rank": 0.08, "score": 9152 }
      ,{ "datetime": "1900-01-05 15:01:38", "days": 5, "rank": 0.07, "score": 9102 }
      ,{ "datetime": "1900-01-05 20:24:26", "days": 5, "rank": 0.08, "score": 9052 }
      ,{ "datetime": "1900-01-05 06:32:24", "days": 5, "rank": 0.07, "score": 9011 }
      ,{ "datetime": "1900-01-06 02:37:24", "days": 5, "rank": 0.1, "score": 8984 }
      ,{ "datetime": "1900-01-06 00:52:43", "days": 5, "rank": 0.1, "score": 8976 }
      ,{ "datetime": "1900-01-05 18:31:08", "days": 5, "rank": 0.07, "score": 8942 }
      ,{ "datetime": "1900-01-05 19:14:51", "days": 5, "rank": 0.09, "score": 8885 }
      ,{ "datetime": "1900-01-06 00:05:48", "days": 5, "rank": 0.11, "score": 8857 }
      ,{ "datetime": "1900-01-06 01:50:03", "days": 5, "rank": 0.13, "score": 8660 }
      ,{ "datetime": "1900-01-05 20:52:15", "days": 5, "rank": 0.11, "score": 8613 }
      ,{ "datetime": "1900-01-05 06:27:44", "days": 5, "rank": 0.1, "score": 8544 }
      ,{ "datetime": "1900-01-05 18:14:01", "days": 5, "rank": 0.12, "score": 8444 }
      ,{ "datetime": "1900-01-05 18:39:18", "days": 5, "rank": 0.13, "score": 8416 }
      ,{ "datetime": "1900-01-05 19:12:19", "days": 5, "rank": 0.14, "score": 8335 }
      ,{ "datetime": "1900-01-05 11:27:37", "days": 5, "rank": 0.12, "score": 8322 }
      ,{ "datetime": "1900-01-05 12:57:46", "days": 5, "rank": 0.13, "score": 8236 }
      ,{ "datetime": "1900-01-06 02:41:00", "days": 5, "rank": 0.2, "score": 8200 }
      ,{ "datetime": "1900-01-06 02:43:15", "days": 5, "rank": 0.32, "score": 8183 }
      ,{ "datetime": "1900-01-05 19:49:52", "days": 5, "rank": 0.16, "score": 8181 }
      ,{ "datetime": "1900-01-05 21:58:20", "days": 5, "rank": 0.18, "score": 8143 }
      ,{ "datetime": "1900-01-06 01:16:53", "days": 5, "rank": 0.2, "score": 8143 }
      ,{ "datetime": "1900-01-06 03:35:00", "days": 5, "rank": 0.23, "score": 8080 }
      ,{ "datetime": "1900-01-05 17:39:01", "days": 5, "rank": 0.18, "score": 8069 }
      ,{ "datetime": "1900-01-05 14:25:14", "days": 5, "rank": 0.17, "score": 8040 }
      ,{ "datetime": "1900-01-06 00:14:50", "days": 5, "rank": 0.22, "score": 8020 }
      ,{ "datetime": "1900-01-06 01:07:26", "days": 5, "rank": 0.24, "score": 7989 }
      ,{ "datetime": "1900-01-06 04:04:47", "days": 5, "rank": 0.26, "score": 7984 }
      ,{ "datetime": "1900-01-05 12:59:25", "days": 5, "rank": 0.18, "score": 7957 }
      ,{ "datetime": "1900-01-06 04:44:33", "days": 5, "rank": 0.27, "score": 7953 }
      ,{ "datetime": "1900-01-05 23:04:45", "days": 5, "rank": 0.24, "score": 7942 }
      ,{ "datetime": "1900-01-06 04:52:24", "days": 5, "rank": 0.29, "score": 7896 }
      ,{ "datetime": "1900-01-05 22:31:49", "days": 5, "rank": 0.24, "score": 7880 }
      ,{ "datetime": "1900-01-06 00:43:53", "days": 5, "rank": 0.3, "score": 7760 }
      ,{ "datetime": "1900-01-05 16:11:52", "days": 5, "rank": 0.24, "score": 7742 }
      ,{ "datetime": "1900-01-05 21:31:10", "days": 5, "rank": 0.28, "score": 7728 }
      ,{ "datetime": "1900-01-05 21:11:08", "days": 5, "rank": 0.29, "score": 7698 }
      ,{ "datetime": "1900-01-05 23:56:18", "days": 5, "rank": 0.31, "score": 7698 }
      ,{ "datetime": "1900-01-05 15:31:23", "days": 5, "rank": 0.25, "score": 7691 }
      ,{ "datetime": "1900-01-06 01:12:15", "days": 5, "rank": 0.32, "score": 7691 }
      ,{ "datetime": "1900-01-06 04:33:06", "days": 5, "rank": 0.35, "score": 7674 }
      ,{ "datetime": "1900-01-05 19:29:09", "days": 5, "rank": 0.28, "score": 7672 }
      ,{ "datetime": "1900-01-05 17:02:16", "days": 5, "rank": 0.27, "score": 7658 }
      ,{ "datetime": "1900-01-05 22:14:43", "days": 5, "rank": 0.31, "score": 7656 }
      ,{ "datetime": "1900-01-05 10:10:19", "days": 5, "rank": 0.24, "score": 7606 }
      ,{ "datetime": "1900-01-06 00:21:25", "days": 5, "rank": 0.35, "score": 7600 }
      ,{ "datetime": "1900-01-06 00:49:31", "days": 5, "rank": 0.37, "score": 7570 }
      ,{ "datetime": "1900-01-06 00:26:33", "days": 5, "rank": 0.37, "score": 7566 }
      ,{ "datetime": "1900-01-06 04:02:33", "days": 5, "rank": 0.41, "score": 7556 }
      ,{ "datetime": "1900-01-05 17:00:43", "days": 5, "rank": 0.3, "score": 7538 }
      ,{ "datetime": "1900-01-05 16:04:27", "days": 5, "rank": 0.31, "score": 7491 }
      ,{ "datetime": "1900-01-05 23:50:39", "days": 5, "rank": 0.39, "score": 7491 }
      ,{ "datetime": "1900-01-06 00:44:46", "days": 5, "rank": 0.41, "score": 7475 }
      ,{ "datetime": "1900-01-05 06:22:57", "days": 5, "rank": 0.28, "score": 7467 }
      ,{ "datetime": "1900-01-05 19:47:59", "days": 5, "rank": 0.35, "score": 7467 }
      ,{ "datetime": "1900-01-06 03:56:39", "days": 5, "rank": 0.46, "score": 7438 }
      ,{ "datetime": "1900-01-05 15:20:09", "days": 5, "rank": 0.32, "score": 7429 }
      ,{ "datetime": "1900-01-05 06:32:24", "days": 5, "rank": 0.29, "score": 7412 }
      ,{ "datetime": "1900-01-05 19:43:23", "days": 5, "rank": 0.38, "score": 7395 }
      ,{ "datetime": "1900-01-05 16:06:26", "days": 5, "rank": 0.36, "score": 7341 }
      ,{ "datetime": "1900-01-06 00:18:08", "days": 5, "rank": 0.47, "score": 7320 }
      ,{ "datetime": "1900-01-05 14:23:42", "days": 5, "rank": 0.36, "score": 7295 }
      ,{ "datetime": "1900-01-05 23:54:14", "days": 5, "rank": 0.48, "score": 7295 }
      ,{ "datetime": "1900-01-06 02:48:58", "days": 5, "rank": 0.51, "score": 7292 }
      ,{ "datetime": "1900-01-05 11:25:32", "days": 5, "rank": 0.35, "score": 7277 }
      ,{ "datetime": "1900-01-05 19:01:29", "days": 5, "rank": 0.41, "score": 7271 }
      ,{ "datetime": "1900-01-05 09:45:26", "days": 5, "rank": 0.35, "score": 7264 }
      ,{ "datetime": "1900-01-05 17:47:23", "days": 5, "rank": 0.44, "score": 7214 }
      ,{ "datetime": "1900-01-05 19:30:45", "days": 5, "rank": 0.44, "score": 7206 }
      ,{ "datetime": "1900-01-05 15:14:46", "days": 5, "rank": 0.41, "score": 7196 }
      ,{ "datetime": "1900-01-06 02:46:14", "days": 5, "rank": 0.57, "score": 7192 }
      ,{ "datetime": "1900-01-05 21:15:59", "days": 5, "rank": 0.52, "score": 7141 }
      ,{ "datetime": "1900-01-05 15:17:35", "days": 5, "rank": 0.45, "score": 7113 }
      ,{ "datetime": "1900-01-05 14:38:53", "days": 5, "rank": 0.45, "score": 7104 }
      ,{ "datetime": "1900-01-05 14:03:15", "days": 5, "rank": 0.45, "score": 7086 }
      ,{ "datetime": "1900-01-05 23:01:35", "days": 5, "rank": 0.57, "score": 7082 }
      ,{ "datetime": "1900-01-05 16:44:44", "days": 5, "rank": 0.49, "score": 7081 }
      ,{ "datetime": "1900-01-05 15:16:09", "days": 5, "rank": 0.46, "score": 7080 }
      ,{ "datetime": "1900-01-05 17:47:34", "days": 5, "rank": 0.5, "score": 7078 }
      ,{ "datetime": "1900-01-05 20:56:29", "days": 5, "rank": 0.56, "score": 7062 }
      ,{ "datetime": "1900-01-05 08:23:05", "days": 5, "rank": 0.42, "score": 7061 }
      ,{ "datetime": "1900-01-06 01:58:17", "days": 5, "rank": 0.65, "score": 7059 }
      ,{ "datetime": "1900-01-05 17:23:02", "days": 5, "rank": 0.48, "score": 7056 }
      ,{ "datetime": "1900-01-05 22:52:54", "days": 5, "rank": 0.59, "score": 7052 }
      ,{ "datetime": "1900-01-05 18:45:50", "days": 5, "rank": 0.53, "score": 7045 }
      ,{ "datetime": "1900-01-05 21:12:10", "days": 5, "rank": 0.58, "score": 7030 }
      ,{ "datetime": "1900-01-05 07:23:49", "days": 5, "rank": 0.44, "score": 7018 }
      ,{ "datetime": "1900-01-05 11:03:12", "days": 5, "rank": 0.47, "score": 6985 }
      ,{ "datetime": "1900-01-06 00:46:55", "days": 5, "rank": 0.69, "score": 6966 }
      ,{ "datetime": "1900-01-05 20:25:33", "days": 5, "rank": 0.61, "score": 6958 }
      ,{ "datetime": "1900-01-05 17:45:41", "days": 5, "rank": 0.57, "score": 6935 }
      ,{ "datetime": "1900-01-05 15:29:42", "days": 5, "rank": 0.56, "score": 6892 }
      ,{ "datetime": "1900-01-05 22:55:50", "days": 5, "rank": 0.7, "score": 6869 }
      ,{ "datetime": "1900-01-05 19:24:09", "days": 5, "rank": 0.66, "score": 6825 }
      ,{ "datetime": "1900-01-06 00:49:17", "days": 5, "rank": 0.78, "score": 6810 }
      ,{ "datetime": "1900-01-06 01:15:46", "days": 5, "rank": 0.81, "score": 6783 }
      ,{ "datetime": "1900-01-05 18:00:53", "days": 5, "rank": 0.66, "score": 6775 }
      ,{ "datetime": "1900-01-05 12:25:24", "days": 5, "rank": 0.59, "score": 6755 }
      ,{ "datetime": "1900-01-06 04:05:56", "days": 5, "rank": 0.89, "score": 6755 }
      ,{ "datetime": "1900-01-05 23:04:32", "days": 5, "rank": 0.78, "score": 6744 }
      ,{ "datetime": "1900-01-06 04:18:46", "days": 5, "rank": 0.9, "score": 6742 }
      ,{ "datetime": "1900-01-06 03:16:33", "days": 5, "rank": 0.88, "score": 6736 }
      ,{ "datetime": "1900-01-05 14:57:08", "days": 5, "rank": 0.64, "score": 6713 }
      ,{ "datetime": "1900-01-05 14:51:45", "days": 5, "rank": 0.66, "score": 6665 }
      ,{ "datetime": "1900-01-06 02:23:29", "days": 5, "rank": 0.97, "score": 6607 }
      ,{ "datetime": "1900-01-06 01:14:40", "days": 5, "rank": 0.96, "score": 6597 }
      ,{ "datetime": "1900-01-05 23:13:40", "days": 5, "rank": 0.88, "score": 6589 }
      ,{ "datetime": "1900-01-05 21:22:38", "days": 5, "rank": 0.87, "score": 6569 }
      ,{ "datetime": "1900-01-06 00:32:13", "days": 5, "rank": 0.96, "score": 6566 }
      ,{ "datetime": "1900-01-06 01:35:15", "days": 5, "rank": 1.01, "score": 6547 }
      ,{ "datetime": "1900-01-05 11:00:15", "days": 5, "rank": 0.7, "score": 6537 }
      ,{ "datetime": "1900-01-06 04:21:11", "days": 5, "rank": 1.08, "score": 6531 }
      ,{ "datetime": "1900-01-06 02:53:38", "days": 5, "rank": 1.02, "score": 6520 }
      ,{ "datetime": "1900-01-06 00:15:14", "days": 5, "rank": 1.01, "score": 6506 }
      ,{ "datetime": "1900-01-05 15:37:35", "days": 5, "rank": 0.79, "score": 6501 }
      ,{ "datetime": "1900-01-05 07:25:47", "days": 5, "rank": 0.7, "score": 6497 }
      ,{ "datetime": "1900-01-06 01:56:53", "days": 5, "rank": 1.07, "score": 6497 }
      ,{ "datetime": "1900-01-06 00:15:57", "days": 5, "rank": 1.02, "score": 6485 }
      ,{ "datetime": "1900-01-06 04:11:14", "days": 5, "rank": 1.12, "score": 6473 }
      ,{ "datetime": "1900-01-05 05:09:30", "days": 5, "rank": 0.73, "score": 6444 }
      ,{ "datetime": "1900-01-06 02:17:43", "days": 5, "rank": 1.14, "score": 6434 }
      ,{ "datetime": "1900-01-05 20:51:10", "days": 5, "rank": 0.97, "score": 6427 }
      ,{ "datetime": "1900-01-06 00:18:57", "days": 5, "rank": 1.09, "score": 6423 }
      ,{ "datetime": "1900-01-06 04:36:30", "days": 5, "rank": 1.21, "score": 6412 }
      ,{ "datetime": "1900-01-05 13:14:28", "days": 5, "rank": 0.81, "score": 6411 }
      ,{ "datetime": "1900-01-05 19:46:45", "days": 5, "rank": 0.97, "score": 6394 }
      ,{ "datetime": "1900-01-06 00:48:27", "days": 5, "rank": 1.14, "score": 6387 }
      ,{ "datetime": "1900-01-05 23:45:44", "days": 5, "rank": 1.12, "score": 6368 }
      ,{ "datetime": "1900-01-06 00:38:34", "days": 5, "rank": 1.16, "score": 6365 }
      ,{ "datetime": "1900-01-05 23:32:36", "days": 5, "rank": 1.12, "score": 6347 }
      ,{ "datetime": "1900-01-06 03:38:10", "days": 5, "rank": 1.28, "score": 6343 }
      ,{ "datetime": "1900-01-06 02:06:24", "days": 5, "rank": 1.25, "score": 6329 }
      ,{ "datetime": "1900-01-05 23:35:10", "days": 5, "rank": 1.17, "score": 6317 }
      ,{ "datetime": "1900-01-05 16:22:21", "days": 5, "rank": 0.92, "score": 6314 }
      ,{ "datetime": "1900-01-05 21:55:32", "days": 5, "rank": 1.11, "score": 6314 }
      ,{ "datetime": "1900-01-05 13:32:47", "days": 5, "rank": 0.89, "score": 6313 }
      ,{ "datetime": "1900-01-05 21:39:13", "days": 5, "rank": 1.1, "score": 6309 }
      ,{ "datetime": "1900-01-06 00:56:21", "days": 5, "rank": 1.24, "score": 6304 }
      ,{ "datetime": "1900-01-05 21:26:55", "days": 5, "rank": 1.1, "score": 6303 }
      ,{ "datetime": "1900-01-06 04:53:49", "days": 5, "rank": 1.38, "score": 6273 }
      ,{ "datetime": "1900-01-06 02:36:54", "days": 5, "rank": 1.35, "score": 6256 }
      ,{ "datetime": "1900-01-06 04:38:56", "days": 5, "rank": 1.43, "score": 6229 }
      ,{ "datetime": "1900-01-06 01:08:19", "days": 5, "rank": 1.33, "score": 6226 }
      ,{ "datetime": "1900-01-05 17:49:53", "days": 5, "rank": 1.06, "score": 6215 }
      ,{ "datetime": "1900-01-06 04:48:35", "days": 5, "rank": 1.47, "score": 6195 }
      ,{ "datetime": "1900-01-05 22:09:06", "days": 5, "rank": 1.24, "score": 6191 }
      ,{ "datetime": "1900-01-06 00:08:00", "days": 5, "rank": 1.33, "score": 6188 }
      ,{ "datetime": "1900-01-06 03:25:41", "days": 5, "rank": 1.47, "score": 6183 }
      ,{ "datetime": "1900-01-06 04:16:52", "days": 5, "rank": 1.5, "score": 6179 }
      ,{ "datetime": "1900-01-05 22:21:48", "days": 5, "rank": 1.28, "score": 6168 }
      ,{ "datetime": "1900-01-06 04:57:33", "days": 5, "rank": 1.54, "score": 6156 }
      ,{ "datetime": "1900-01-05 23:52:41", "days": 5, "rank": 1.38, "score": 6138 }
      ,{ "datetime": "1900-01-05 22:42:13", "days": 5, "rank": 1.33, "score": 6130 }
      ,{ "datetime": "1900-01-05 21:28:52", "days": 5, "rank": 1.29, "score": 6122 }
      ,{ "datetime": "1900-01-06 02:09:59", "days": 5, "rank": 1.47, "score": 6114 }
      ,{ "datetime": "1900-01-05 23:22:52", "days": 5, "rank": 1.4, "score": 6101 }
      ,{ "datetime": "1900-01-06 02:48:08", "days": 5, "rank": 1.61, "score": 6062 }
      ,{ "datetime": "1900-01-05 16:26:05", "days": 5, "rank": 1.16, "score": 6060 }
      ,{ "datetime": "1900-01-06 00:45:34", "days": 5, "rank": 1.52, "score": 6047 }
      ,{ "datetime": "1900-01-05 23:00:54", "days": 5, "rank": 1.27, "score": 6037 }
      ,{ "datetime": "1900-01-05 14:25:59", "days": 5, "rank": 1.14, "score": 6034 }
      ,{ "datetime": "1900-01-06 04:56:47", "days": 5, "rank": 1.72, "score": 6031 }
      ,{ "datetime": "1900-01-05 07:52:36", "days": 5, "rank": 1.06, "score": 6028 }
      ,{ "datetime": "1900-01-05 19:20:09", "days": 5, "rank": 1.31, "score": 6028 }
      ,{ "datetime": "1900-01-05 23:13:06", "days": 5, "rank": 1.48, "score": 6025 }
      ,{ "datetime": "1900-01-05 13:32:42", "days": 5, "rank": 1.15, "score": 6013 }
      ,{ "datetime": "1900-01-05 15:37:26", "days": 5, "rank": 1.22, "score": 5996 }
      ,{ "datetime": "1900-01-06 03:07:29", "days": 5, "rank": 1.71, "score": 5988 }
      ,{ "datetime": "1900-01-05 22:39:37", "days": 5, "rank": 1.5, "score": 5987 }
      ,{ "datetime": "1900-01-06 02:23:07", "days": 5, "rank": 1.71, "score": 5981 }
      ,{ "datetime": "1900-01-05 13:32:13", "days": 5, "rank": 1.17, "score": 5979 }
      ,{ "datetime": "1900-01-05 22:37:28", "days": 5, "rank": 1.5, "score": 5979 }
      ,{ "datetime": "1900-01-05 09:17:36", "days": 5, "rank": 1.1, "score": 5972 }
      ,{ "datetime": "1900-01-05 17:50:05", "days": 5, "rank": 1.32, "score": 5964 }
      ,{ "datetime": "1900-01-06 01:20:52", "days": 5, "rank": 1.563, "score": 5957 }
      ,{ "datetime": "1900-01-06 01:12:26", "days": 5, "rank": 1.63, "score": 5957 }
      ,{ "datetime": "1900-01-05 16:46:35", "days": 5, "rank": 1.29, "score": 5951 }
      ,{ "datetime": "1900-01-05 15:48:11", "days": 5, "rank": 1.27, "score": 5935 }
      ,{ "datetime": "1900-01-06 03:11:40", "days": 5, "rank": 1.83, "score": 5914 }
      ,{ "datetime": "1900-01-06 02:42:13", "days": 5, "rank": 1.81, "score": 5909 }
      ,{ "datetime": "1900-01-06 04:09:48", "days": 5, "rank": 1.89, "score": 5902 }
      ,{ "datetime": "1900-01-05 15:44:46", "days": 5, "rank": 1.33, "score": 5876 }
      ,{ "datetime": "1900-01-05 19:00:19", "days": 5, "rank": 1.44, "score": 5876 }
      ,{ "datetime": "1900-01-05 22:32:05", "days": 5, "rank": 1.62, "score": 5866 }
      ,{ "datetime": "1900-01-06 03:40:14", "days": 5, "rank": 1.92, "score": 5861 }
      ,{ "datetime": "1900-01-06 02:53:44", "days": 5, "rank": 1.89, "score": 5858 }
      ,{ "datetime": "1900-01-05 11:28:38", "days": 5, "rank": 1.23, "score": 5851 }
      ,{ "datetime": "1900-01-05 19:26:36", "days": 5, "rank": 1.49, "score": 5850 }
      ,{ "datetime": "1900-01-06 04:15:28", "days": 5, "rank": 1.98, "score": 5841 }
      ,{ "datetime": "1900-01-06 01:08:52", "days": 5, "rank": 1.85, "score": 5814 }
      ,{ "datetime": "1900-01-06 02:54:36", "days": 5, "rank": 1.99, "score": 5791 }
      ,{ "datetime": "1900-01-05 23:08:17", "days": 5, "rank": 1.74, "score": 5790 }
      ,{ "datetime": "1900-01-06 01:46:13", "days": 5, "rank": 1.94, "score": 5782 }
      ,{ "datetime": "1900-01-06 01:28:28", "days": 5, "rank": 1.91, "score": 5779 }
      ,{ "datetime": "1900-01-06 01:27:41", "days": 5, "rank": 1.87, "score": 5762 }
      ,{ "datetime": "1900-01-06 01:15:52", "days": 5, "rank": 1.92, "score": 5753 }
      ,{ "datetime": "1900-01-05 11:12:54", "days": 5, "rank": 1.29, "score": 5750 }
      ,{ "datetime": "1900-01-05 16:58:27", "days": 5, "rank": 1.48, "score": 5746 }
      ,{ "datetime": "1900-01-06 00:54:35", "days": 5, "rank": 1.92, "score": 5743 }
      ,{ "datetime": "1900-01-06 01:05:16", "days": 5, "rank": 1.94, "score": 5737 }
      ,{ "datetime": "1900-01-06 02:52:48", "days": 5, "rank": 2.07, "score": 5727 }
      ,{ "datetime": "1900-01-06 03:18:10", "days": 5, "rank": 2.1, "score": 5718 }
      ,{ "datetime": "1900-01-05 19:28:21", "days": 5, "rank": 1.62, "score": 5709 }
      ,{ "datetime": "1900-01-05 21:29:41", "days": 5, "rank": 1.72, "score": 5706 }
      ,{ "datetime": "1900-01-06 01:17:46", "days": 5, "rank": 1.93, "score": 5689 }
      ,{ "datetime": "1900-01-05 23:55:03", "days": 5, "rank": 1.91, "score": 5688 }
      ,{ "datetime": "1900-01-05 18:53:17", "days": 5, "rank": 1.63, "score": 5683 }
      ,{ "datetime": "1900-01-06 00:04:31", "days": 5, "rank": 1.93, "score": 5682 }
      ,{ "datetime": "1900-01-06 01:42:34", "days": 5, "rank": 2.07, "score": 5678 }
      ,{ "datetime": "1900-01-05 20:29:35", "days": 5, "rank": 1.71, "score": 5665 }
      ,{ "datetime": "1900-01-05 23:02:33", "days": 5, "rank": 1.89, "score": 5656 }
      ,{ "datetime": "1900-01-06 00:17:05", "days": 5, "rank": 1.99, "score": 5639 }
      ,{ "datetime": "1900-01-05 21:08:38", "days": 5, "rank": 1.81, "score": 5604 }
      ,{ "datetime": "1900-01-05 17:46:40", "days": 5, "rank": 1.65, "score": 5595 }
      ,{ "datetime": "1900-01-06 03:34:40", "days": 5, "rank": 2.31, "score": 5595 }
      ,{ "datetime": "1900-01-06 01:55:24", "days": 5, "rank": 2.02, "score": 5578 }
      ,{ "datetime": "1900-01-05 15:11:10", "days": 5, "rank": 1.57, "score": 5568 }
      ,{ "datetime": "1900-01-06 02:30:50", "days": 5, "rank": 2.29, "score": 5558 }
      ,{ "datetime": "1900-01-05 23:27:07", "days": 5, "rank": 2.04, "score": 5548 }
      ,{ "datetime": "1900-01-06 01:48:10", "days": 5, "rank": 2.25, "score": 5547 }
      ,{ "datetime": "1900-01-06 04:17:29", "days": 5, "rank": 2.42, "score": 5542 }
      ,{ "datetime": "1900-01-06 01:53:56", "days": 5, "rank": 2.25, "score": 5540 }
      ,{ "datetime": "1900-01-06 04:56:10", "days": 5, "rank": 2.46, "score": 5539 }
      ,{ "datetime": "1900-01-05 11:35:07", "days": 5, "rank": 1.49, "score": 5532 }
      ,{ "datetime": "1900-01-05 12:38:12", "days": 5, "rank": 1.53, "score": 5521 }
      ,{ "datetime": "1900-01-06 01:07:31", "days": 5, "rank": 2.23, "score": 5513 }
      ,{ "datetime": "1900-01-05 20:43:17", "days": 5, "rank": 1.89, "score": 5503 }
      ,{ "datetime": "1900-01-05 10:06:46", "days": 5, "rank": 1.48, "score": 5502 }
      ,{ "datetime": "1900-01-05 11:29:03", "days": 5, "rank": 1.5, "score": 5500 }
      ,{ "datetime": "1900-01-05 15:44:26", "days": 5, "rank": 1.5, "score": 5500 }
      ,{ "datetime": "1900-01-05 20:58:19", "days": 5, "rank": 1.9, "score": 5500 }
      ,{ "datetime": "1900-01-05 17:25:09", "days": 5, "rank": 1.75, "score": 5473 }
      ,{ "datetime": "1900-01-06 04:44:57", "days": 5, "rank": 2.57, "score": 5459 }
      ,{ "datetime": "1900-01-06 04:39:28", "days": 5, "rank": 2.57, "score": 5455 }
      
      ,{ "datetime": "1900-01-06 03:51:20", "days": 5, "rank": 2.54, "score": 5443 }
      ,{ "datetime": "1900-01-05 23:57:35", "days": 5, "rank": 2.18, "score": 5441 }
      ,{ "datetime": "1900-01-06 03:03:01", "days": 5, "rank": 2.48, "score": 5425 }
      ,{ "datetime": "1900-01-06 02:56:23", "days": 5, "rank": 2.51, "score": 5418 }
      ,{ "datetime": "1900-01-05 11:38:28", "days": 5, "rank": 1.59, "score": 5406 }
      ,{ "datetime": "1900-01-05 19:14:59", "days": 5, "rank": 1.91, "score": 5397 }
      ,{ "datetime": "1900-01-06 03:20:05", "days": 5, "rank": 2.57, "score": 5389 }
      ,{ "datetime": "1900-01-05 23:26:49", "days": 5, "rank": 2.21, "score": 5381 }
      ,{ "datetime": "1900-01-06 01:51:18", "days": 5, "rank": 2.48, "score": 5352 }
      ,{ "datetime": "1900-01-05 06:43:01", "days": 5, "rank": 1.56, "score": 5351 }
      ,{ "datetime": "1900-01-06 01:51:41", "days": 5, "rank": 2.49, "score": 5348 }
      ,{ "datetime": "1900-01-05 08:10:36", "days": 5, "rank": 1.59, "score": 5342 }
      ,{ "datetime": "1900-01-06 01:04:14", "days": 5, "rank": 2.34, "score": 5333 }
      ,{ "datetime": "1900-01-05 07:17:00", "days": 5, "rank": 1.59, "score": 5328 }
      ,{ "datetime": "1900-01-05 23:36:54", "days": 5, "rank": 2.3, "score": 5328 }
      ,{ "datetime": "1900-01-05 07:58:46", "days": 5, "rank": 1.5, "score": 5276 }
      ,{ "datetime": "1900-01-05 22:30:25", "days": 5, "rank": 2.22, "score": 5254 }
      ,{ "datetime": "1900-01-05 09:45:42", "days": 5, "rank": 1.68, "score": 5239 }
      ,{ "datetime": "1900-01-05 13:36:19", "days": 5, "rank": 1.8, "score": 5216 }
      
      
      ,{ "datetime": "1900-01-06 01:43:22", "days": 5, "rank": 2.65, "score": 5197 }
      ,{ "datetime": "1900-01-06 03:20:20", "days": 5, "rank": 2.86, "score": 5183 }
      ,{ "datetime": "1900-01-05 21:45:11", "days": 5, "rank": 2.28, "score": 5181 }
      ,{ "datetime": "1900-01-06 02:53:41", "days": 5, "rank": 2.82, "score": 5178 }
      ,{ "datetime": "1900-01-05 23:43:32", "days": 5, "rank": 2.51, "score": 5160 }
      ,{ "datetime": "1900-01-05 12:30:15", "days": 5, "rank": 1.81, "score": 5153 }
      ,{ "datetime": "1900-01-06 02:59:55", "days": 5, "rank": 2.88, "score": 5140 }
      ,{ "datetime": "1900-01-05 14:55:45", "days": 5, "rank": 1.91, "score": 5135 }
      ,{ "datetime": "1900-01-05 17:32:57", "days": 5, "rank": 2.1, "score": 5089 }
      ,{ "datetime": "1900-01-05 16:12:25", "days": 5, "rank": 2.07, "score": 5030 }
      ,{ "datetime": "1900-01-06 03:39:31", "days": 5, "rank": 3.12, "score": 5001 }
      ,{ "datetime": "1900-01-06 02:37:34", "days": 5, "rank": 3.04, "score": 4974 }
      ,{ "datetime": "1900-01-06 02:09:01", "days": 5, "rank": 2.99, "score": 4970 }
      ,{ "datetime": "1900-01-05 23:11:58", "days": 5, "rank": 2.58, "score": 4943 }
      ,{ "datetime": "1900-01-06 01:22:08", "days": 5, "rank": 3.09, "score": 4783 }
      ,{ "datetime": "1900-01-05 16:09:03", "days": 5, "rank": 2.26, "score": 4773 }
      ,{ "datetime": "1900-01-05 22:00:07", "days": 5, "rank": 2.7, "score": 4773 }
      ,{ "datetime": "1900-01-05 20:00:37", "days": 5, "rank": 2.55, "score": 4738 }
      ,{ "datetime": "1900-01-05 21:34:46", "days": 5, "rank": 2.69, "score": 4729 }
      ,{ "datetime": "1900-01-06 04:22:22", "days": 5, "rank": 3.5, "score": 4707 }
      ,{ "datetime": "1900-01-05 06:17:32", "days": 5, "rank": 2.03, "score": 4704 }
      ,{ "datetime": "1900-01-05 23:50:25", "days": 5, "rank": 2.99, "score": 4704 }
      ,{ "datetime": "1900-01-06 04:06:59", "days": 5, "rank": 3.48, "score": 4700 }
      ,{ "datetime": "1900-01-05 20:55:08", "days": 5, "rank": 2.58, "score": 4639 }
      ,{ "datetime": "1900-01-05 08:50:55", "days": 5, "rank": 2.11, "score": 4628 }
      ,{ "datetime": "1900-01-05 23:45:23", "days": 5, "rank": 3.16, "score": 4528 }
      ,{ "datetime": "1900-01-05 21:50:23", "days": 5, "rank": 2.95, "score": 4518 }
      ,{ "datetime": "1900-01-05 19:41:48", "days": 5, "rank": 2.75, "score": 4514 }
      ,{ "datetime": "1900-01-05 20:35:17", "days": 5, "rank": 2.82, "score": 4509 }
      ,{ "datetime": "1900-01-06 04:37:05", "days": 5, "rank": 3.78, "score": 4505 }
      ,{ "datetime": "1900-01-05 12:22:37", "days": 5, "rank": 1.93, "score": 4447 }
      ,{ "datetime": "1900-01-06 02:36:41", "days": 5, "rank": 3.67, "score": 4431 }
      ,{ "datetime": "1900-01-06 03:21:39", "days": 5, "rank": 3.9, "score": 4358 }
      ,{ "datetime": "1900-01-05 20:59:04", "days": 5, "rank": 3.1, "score": 4296 }
      ,{ "datetime": "1900-01-05 13:09:51", "days": 5, "rank": 2.55, "score": 4279 }
      ,{ "datetime": "1900-01-05 16:01:49", "days": 5, "rank": 2.74, "score": 4275 }
      ,{ "datetime": "1900-01-05 10:07:29", "days": 5, "rank": 2.54, "score": 4174 }
      ,{ "datetime": "1900-01-05 16:31:26", "days": 5, "rank": 2.9, "score": 4166 }
      ,{ "datetime": "1900-01-06 00:32:28", "days": 5, "rank": 3.83, "score": 4129 }
      ,{ "datetime": "1900-01-06 00:07:01", "days": 5, "rank": 3.7, "score": 4112 }
      ,{ "datetime": "1900-01-05 07:39:44", "days": 5, "rank": 2.59, "score": 4082 }
      ,{ "datetime": "1900-01-05 16:31:00", "days": 5, "rank": 3.01, "score": 4070 }
      ,{ "datetime": "1900-01-05 23:05:30", "days": 5, "rank": 3.72, "score": 4045 }
      ,{ "datetime": "1900-01-06 01:01:53", "days": 5, "rank": 3.55, "score": 4011 }
      ,{ "datetime": "1900-01-05 16:27:20", "days": 5, "rank": 3.09, "score": 4007 }
      ,{ "datetime": "1900-01-05 15:48:07", "days": 5, "rank": 3.03, "score": 3998 }
      ,{ "datetime": "1900-01-05 23:43:41", "days": 5, "rank": 4.04, "score": 3916 }
      ,{ "datetime": "1900-01-05 23:10:28", "days": 5, "rank": 4.04, "score": 3855 }
      ,{ "datetime": "1900-01-06 00:32:02", "days": 5, "rank": 4.23, "score": 3855 }
      ,{ "datetime": "1900-01-05 22:36:23", "days": 5, "rank": 3.96, "score": 3839 }
      ,{ "datetime": "1900-01-05 10:49:25", "days": 5, "rank": 3.01, "score": 3796 }
      ,{ "datetime": "1900-01-06 03:19:16", "days": 5, "rank": 5.09, "score": 3702 }
      ,{ "datetime": "1900-01-06 00:14:06", "days": 5, "rank": 4.53, "score": 3673 }
      ,{ "datetime": "1900-01-05 20:39:41", "days": 5, "rank": 4.03, "score": 3616 }
      ,{ "datetime": "1900-01-06 00:27:05", "days": 5, "rank": 4.73, "score": 3606 }
      ,{ "datetime": "1900-01-06 00:11:30", "days": 5, "rank": 4.7, "score": 3592 }
      ,{ "datetime": "1900-01-05 20:43:37", "days": 5, "rank": 4.15, "score": 3561 }
      ,{ "datetime": "1900-01-05 21:07:19", "days": 5, "rank": 4.26, "score": 3538 }
      ,{ "datetime": "1900-01-06 03:01:58", "days": 5, "rank": 5.37, "score": 3535 }
      ,{ "datetime": "1900-01-06 04:00:50", "days": 5, "rank": 5.57, "score": 3529 }
      ,{ "datetime": "1900-01-05 20:20:43", "days": 5, "rank": 4.12, "score": 3504 }
      ,{ "datetime": "1900-01-06 04:43:54", "days": 5, "rank": 5.84, "score": 3465 }
      ,{ "datetime": "1900-01-05 22:23:10", "days": 5, "rank": 3.83, "score": 3454 }
      ,{ "datetime": "1900-01-05 22:47:31", "days": 5, "rank": 4.77, "score": 3427 }
      ,{ "datetime": "1900-01-06 02:43:22", "days": 5, "rank": 5.76, "score": 3370 }
      ,{ "datetime": "1900-01-06 01:01:11", "days": 5, "rank": 5.31, "score": 3351 }
      ,{ "datetime": "1900-01-06 04:22:48", "days": 5, "rank": 6.1, "score": 3351 }
      ,{ "datetime": "1900-01-05 22:40:24", "days": 5, "rank": 5.1, "score": 3259 }
      ,{ "datetime": "1900-01-06 02:57:12", "days": 5, "rank": 6.12, "score": 3223 }
      ,{ "datetime": "1900-01-05 20:31:32", "days": 5, "rank": 5.03, "score": 3126 }
      ,{ "datetime": "1900-01-05 12:18:09", "days": 5, "rank": 4.21, "score": 3005 }
      ,{ "datetime": "1900-01-05 16:17:31", "days": 5, "rank": 4.85, "score": 2979 }
      ,{ "datetime": "1900-01-05 07:56:17", "days": 5, "rank": 4.26, "score": 2975 }
      ,{ "datetime": "1900-01-05 22:38:25", "days": 5, "rank": 5.85, "score": 2958 }
      ,{ "datetime": "1900-01-05 11:40:25", "days": 5, "rank": 4.7, "score": 2833 }
      ,{ "datetime": "1900-01-05 14:09:55", "days": 5, "rank": 4.09, "score": 2823 }
      ,{ "datetime": "1900-01-05 14:22:31", "days": 5, "rank": 4.967, "score": 2822 }
      ,{ "datetime": "1900-01-05 22:39:28", "days": 5, "rank": 6.26, "score": 2822 }
      ,{ "datetime": "1900-01-05 20:23:10", "days": 5, "rank": 5.84, "score": 2796 }
      ,{ "datetime": "1900-01-05 17:52:21", "days": 5, "rank": 5.5, "score": 2793 }
      ,{ "datetime": "1900-01-05 22:10:11", "days": 5, "rank": 6.44, "score": 2723 }
      ,{ "datetime": "1900-01-05 14:08:28", "days": 5, "rank": 5.34, "score": 2626 }
      ,{ "datetime": "1900-01-05 23:23:20", "days": 5, "rank": 7.14, "score": 2593 }
      ,{ "datetime": "1900-01-05 23:08:48", "days": 5, "rank": 7.23, "score": 2560 }
      ,{ "datetime": "1900-01-05 23:07:59", "days": 5, "rank": 7.23, "score": 2560 }
      ,{ "datetime": "1900-01-05 15:31:56", "days": 5, "rank": 5.85, "score": 2540 }
      ,{ "datetime": "1900-01-05 18:13:17", "days": 5, "rank": 6.26, "score": 2534 }
      ,{ "datetime": "1900-01-05 15:23:32", "days": 5, "rank": 6.15, "score": 2433 }
      ,{ "datetime": "1900-01-05 22:37:58", "days": 5, "rank": 7.62, "score": 2393 }
      ,{ "datetime": "1900-01-06 02:03:41", "days": 5, "rank": 8.86, "score": 2351 }
      ,{ "datetime": "1900-01-05 15:10:36", "days": 5, "rank": 6.35, "score": 2340 }
      ,{ "datetime": "1900-01-05 20:20:01", "days": 5, "rank": 7.33, "score": 2316 }
      ,{ "datetime": "1900-01-05 23:09:12", "days": 5, "rank": 8.02, "score": 2306 }
      ,{ "datetime": "1900-01-05 17:37:55", "days": 5, "rank": 7.27, "score": 2204 }
      ,{ "datetime": "1900-01-05 21:33:56", "days": 5, "rank": 8.17, "score": 2182 }
      ,{ "datetime": "1900-01-06 03:51:54", "days": 5, "rank": 10.86, "score": 2088 }
      ,{ "datetime": "1900-01-06 01:11:13", "days": 5, "rank": 10.18, "score": 2040 }
      ,{ "datetime": "1900-01-05 22:00:59", "days": 5, "rank": 8.88, "score": 2038 }
      ,{ "datetime": "1900-01-05 06:21:13", "days": 5, "rank": 6.13, "score": 1862 }
      ,{ "datetime": "1900-01-05 21:07:59", "days": 5, "rank": 9.83, "score": 1787 }
      ,{ "datetime": "1900-01-05 14:07:28", "days": 5, "rank": 8.47, "score": 1763 }
      ,{ "datetime": "1900-01-05 20:37:31", "days": 5, "rank": 10.4, "score": 1641 }
      ,{ "datetime": "1900-01-05 08:22:31", "days": 5, "rank": 8.9, "score": 1543 }
      ,{ "datetime": "1900-01-06 01:04:49", "days": 5, "rank": 12.94, "score": 1499 }
      ,{ "datetime": "1900-01-05 20:39:50", "days": 5, "rank": 11.61, "score": 1439 }
      ,{ "datetime": "1900-01-05 23:05:52", "days": 5, "rank": 13.22, "score": 1362 }
      ,{ "datetime": "1900-01-05 23:12:09", "days": 5, "rank": 13.65, "score": 1312 }
      ,{ "datetime": "1900-01-05 15:38:48", "days": 5, "rank": 12.2, "score": 1175 }
      ,{ "datetime": "1900-01-05 22:41:29", "days": 5, "rank": 14.76, "score": 1119 }
      ,{ "datetime": "1900-01-05 18:05:23", "days": 5, "rank": 13.79, "score": 1047 }
      ,{ "datetime": "1900-01-05 19:04:42", "days": 5, "rank": 14.43, "score": 1005 }
      ,{ "datetime": "1900-01-05 20:09:52", "days": 5, "rank": 15.99, "score": 872 }
      ,{ "datetime": "1900-01-05 22:32:16", "days": 5, "rank": 22.31, "score": 409 }
      ,{ "datetime": "1900-01-05 11:09:00", "days": 5, "rank": 19.75, "score": 4 }
      
      
      
      
      
      
      ,{ "datetime": "1900-01-06 07:44:00", "days": 6, "rank": 0.02, "score": 12151 }
      ,{ "datetime": "1900-01-06 09:07:30", "days": 6, "rank": 0.02, "score": 12054 }
      ,{ "datetime": "1900-01-06 06:02:46", "days": 6, "rank": 0.02, "score": 11826 }
      ,{ "datetime": "1900-01-06 08:34:59", "days": 6, "rank": 0.02, "score": 11771 }
      ,{ "datetime": "1900-01-06 05:28:24", "days": 6, "rank": 0.02, "score": 11629 }
      ,{ "datetime": "1900-01-06 07:21:25", "days": 6, "rank": 0.02, "score": 11548 }
      ,{ "datetime": "1900-01-06 07:42:45", "days": 6, "rank": 0.03, "score": 11146 }
      ,{ "datetime": "1900-01-06 07:17:29", "days": 6, "rank": 0.03, "score": 11108 }
      ,{ "datetime": "1900-01-06 06:37:20", "days": 6, "rank": 0.03, "score": 11097 }
      ,{ "datetime": "1900-01-06 05:43:32", "days": 6, "rank": 0.04, "score": 10841 }
      ,{ "datetime": "1900-01-06 05:09:36", "days": 6, "rank": 0.04, "score": 10706 }
      ,{ "datetime": "1900-01-06 06:05:37", "days": 6, "rank": 0.05, "score": 10592 }
      ,{ "datetime": "1900-01-06 06:07:58", "days": 6, "rank": 0.05, "score": 10533 }
      ,{ "datetime": "1900-01-06 06:36:02", "days": 6, "rank": 0.05, "score": 10412 }
      ,{ "datetime": "1900-01-06 05:55:54", "days": 6, "rank": 0.07, "score": 9678 }
      ,{ "datetime": "1900-01-06 05:49:43", "days": 6, "rank": 0.09, "score": 9157 }
      
      ,{ "datetime": "1900-01-06 05:43:15", "days": 6, "rank": 0.13, "score": 8651 }
      ,{ "datetime": "1900-01-06 05:48:17", "days": 6, "rank": 0.29, "score": 7903 }
      ,{ "datetime": "1900-01-06 08:29:40", "days": 6, "rank": 0.32, "score": 7818 }
      ,{ "datetime": "1900-01-06 06:42:48", "days": 6, "rank": 0.34, "score": 7731 }
      ,{ "datetime": "1900-01-06 06:22:02", "days": 6, "rank": 0.35, "score": 7723 }
      ,{ "datetime": "1900-01-06 05:15:12", "days": 6, "rank": 0.38, "score": 7628 }
      ,{ "datetime": "1900-01-06 06:57:45", "days": 6, "rank": 0.41, "score": 7565 }
      ,{ "datetime": "1900-01-06 05:15:31", "days": 6, "rank": 0.48, "score": 7402 }
      ,{ "datetime": "1900-01-06 06:49:57", "days": 6, "rank": 0.49, "score": 7397 }
      ,{ "datetime": "1900-01-06 05:07:53", "days": 6, "rank": 0.5, "score": 7372 }
      ,{ "datetime": "1900-01-06 05:09:47", "days": 6, "rank": 0.55, "score": 7271 }
      ,{ "datetime": "1900-01-06 06:25:55", "days": 6, "rank": 0.63, "score": 7117 }
      ,{ "datetime": "1900-01-06 05:00:00", "days": 6, "rank": 0.7, "score": 7031 }
      ,{ "datetime": "1900-01-06 05:41:32", "days": 6, "rank": 0.72, "score": 7006 }
      ,{ "datetime": "1900-01-06 06:04:21", "days": 6, "rank": 0.73, "score": 6991 }
      
      ,{ "datetime": "1900-01-06 07:00:30", "days": 6, "rank": 0.78, "score": 6912 }
      ,{ "datetime": "1900-01-06 09:01:42", "days": 6, "rank": 0.82, "score": 6852 }
      ,{ "datetime": "1900-01-06 07:38:10", "days": 6, "rank": 0.83, "score": 6841 }
      ,{ "datetime": "1900-01-06 05:12:33", "days": 6, "rank": 0.85, "score": 6825 }
      ,{ "datetime": "1900-01-06 06:54:12", "days": 6, "rank": 0.87, "score": 6792 }
      
      ,{ "datetime": "1900-01-06 05:48:16", "days": 6, "rank": 0.88, "score": 6778 }
      ,{ "datetime": "1900-01-06 07:54:34", "days": 6, "rank": 0.9, "score": 6756 }
      
      
      ,{ "datetime": "1900-01-06 08:56:13", "days": 6, "rank": 0.91, "score": 6744 }
      ,{ "datetime": "1900-01-06 06:40:57", "days": 6, "rank": 0.92, "score": 6728 }
      ,{ "datetime": "1900-01-06 06:23:28", "days": 6, "rank": 0.99, "score": 6646 }
      ,{ "datetime": "1900-01-06 05:00:00", "days": 6, "rank": 1, "score": 6637 }
      ,{ "datetime": "1900-01-06 07:58:16", "days": 6, "rank": 1.01, "score": 6628 }
      ,{ "datetime": "1900-01-06 06:49:29", "days": 6, "rank": 1.02, "score": 6609 }
      ,{ "datetime": "1900-01-06 07:30:27", "days": 6, "rank": 1.04, "score": 6597 }
      ,{ "datetime": "1900-01-06 06:25:07", "days": 6, "rank": 1.08, "score": 6554 }
      
      ,{ "datetime": "1900-01-06 08:24:12", "days": 6, "rank": 1.16, "score": 6470 }
      
      ,{ "datetime": "1900-01-06 06:43:52", "days": 6, "rank": 1.35, "score": 6309 }
      
      ,{ "datetime": "1900-01-06 05:08:24", "days": 6, "rank": 1.46, "score": 6219 }
      
      ,{ "datetime": "1900-01-06 08:21:34", "days": 6, "rank": 1.51, "score": 6185 }
      ,{ "datetime": "1900-01-06 08:39:51", "days": 6, "rank": 1.59, "score": 6122 }
      
      ,{ "datetime": "1900-01-06 08:07:00", "days": 6, "rank": 1.62, "score": 6102 }
      ,{ "datetime": "1900-01-06 08:01:16", "days": 6, "rank": 1.64, "score": 6089 }
      ,{ "datetime": "1900-01-06 08:31:40", "days": 6, "rank": 1.65, "score": 6082 }
      ,{ "datetime": "1900-01-06 07:57:55", "days": 6, "rank": 1.68, "score": 6057 }
      
      ,{ "datetime": "1900-01-06 08:13:13", "days": 6, "rank": 1.73, "score": 6028 }
      ,{ "datetime": "1900-01-06 06:49:13", "days": 6, "rank": 1.76, "score": 6012 }
      ,{ "datetime": "1900-01-06 05:02:08", "days": 6, "rank": 1.77, "score": 6006 }
      ,{ "datetime": "1900-01-06 07:22:35", "days": 6, "rank": 1.96, "score": 5870 }
      ,{ "datetime": "1900-01-06 06:57:08", "days": 6, "rank": 1.97, "score": 5866 }
      ,{ "datetime": "1900-01-06 05:54:34", "days": 6, "rank": 1.99, "score": 5855 }
      ,{ "datetime": "1900-01-06 05:00:00", "days": 6, "rank": 2, "score": 5848 }
      ,{ "datetime": "1900-01-06 06:12:08", "days": 6, "rank": 2.23, "score": 5689 }
      
      ,{ "datetime": "1900-01-06 08:46:15", "days": 6, "rank": 2.24, "score": 5682 }
      ,{ "datetime": "1900-01-06 09:00:25", "days": 6, "rank": 2.27, "score": 5667 }
      ,{ "datetime": "1900-01-06 05:01:46", "days": 6, "rank": 2.39, "score": 5592 }
      ,{ "datetime": "1900-01-06 05:11:20", "days": 6, "rank": 2.41, "score": 5578 }
      ,{ "datetime": "1900-01-06 09:09:33", "days": 6, "rank": 2.43, "score": 5567 }
      ,{ "datetime": "1900-01-06 05:08:16", "days": 6, "rank": 2.44, "score": 5558 }
      ,{ "datetime": "1900-01-06 07:12:13", "days": 6, "rank": 2.46, "score": 5547 }
      ,{ "datetime": "1900-01-06 07:49:35", "days": 6, "rank": 2.52, "score": 5506 }
      ,{ "datetime": "1900-01-06 06:30:44", "days": 6, "rank": 2.53, "score": 5505 }
      
      ,{ "datetime": "1900-01-06 07:17:14", "days": 6, "rank": 2.57, "score": 5473 }
      ,{ "datetime": "1900-01-06 05:25:36", "days": 6, "rank": 2.61, "score": 5448 }
      ,{ "datetime": "1900-01-06 06:09:56", "days": 6, "rank": 2.67, "score": 5440 }
      
      ,{ "datetime": "1900-01-06 08:58:43", "days": 6, "rank": 2.67, "score": 5400 }
      ,{ "datetime": "1900-01-06 06:27:31", "days": 6, "rank": 2.76, "score": 5345 }
      ,{ "datetime": "1900-01-06 05:19:53", "days": 6, "rank": 2.79, "score": 5322 }
      ,{ "datetime": "1900-01-06 05:09:53", "days": 6, "rank": 2.8, "score": 5317 }
      ,{ "datetime": "1900-01-06 06:18:26", "days": 6, "rank": 2.88, "score": 5265 }
      ,{ "datetime": "1900-01-06 07:25:35", "days": 6, "rank": 2.9, "score": 5252 }
      ,{ "datetime": "1900-01-06 06:58:53", "days": 6, "rank": 2.92, "score": 5241 }
      ,{ "datetime": "1900-01-06 06:49:11", "days": 6, "rank": 2.98, "score": 5197 }
      ,{ "datetime": "1900-01-06 08:40:27", "days": 6, "rank": 2.99, "score": 5191 }
      
      ,{ "datetime": "1900-01-06 05:04:20", "days": 6, "rank": 3, "score": 5185 }
      
      ,{ "datetime": "1900-01-06 06:17:32", "days": 6, "rank": 3.02, "score": 5172 }
      ,{ "datetime": "1900-01-06 05:46:38", "days": 6, "rank": 3.06, "score": 5135 }
      ,{ "datetime": "1900-01-06 07:26:54", "days": 6, "rank": 3.12, "score": 5089 }
      
      ,{ "datetime": "1900-01-06 07:53:09", "days": 6, "rank": 3.17, "score": 5050 }
      ,{ "datetime": "1900-01-06 08:18:34", "days": 6, "rank": 3.42, "score": 4833 }
      ,{ "datetime": "1900-01-06 05:12:39", "days": 6, "rank": 3.7, "score": 4612 }
      ,{ "datetime": "1900-01-06 05:04:32", "days": 6, "rank": 3.97, "score": 4427 }
      ,{ "datetime": "1900-01-06 05:00:34", "days": 6, "rank": 4.28, "score": 4231 }
      ,{ "datetime": "1900-01-06 08:57:16", "days": 6, "rank": 4.53, "score": 4092 }
      ,{ "datetime": "1900-01-06 11:19:55", "days": 6, "rank": 4.55, "score": 4085 }
      ,{ "datetime": "1900-01-06 08:46:59", "days": 6, "rank": 4.61, "score": 4053 }
      ,{ "datetime": "1900-01-06 05:53:05", "days": 6, "rank": 4.9, "score": 3903 }
      ,{ "datetime": "1900-01-06 06:47:46", "days": 6, "rank": 4.96, "score": 3874 }
      
      ,{ "datetime": "1900-01-06 08:06:57", "days": 6, "rank": 5, "score": 3855 }
      ,{ "datetime": "1900-01-06 09:33:53", "days": 6, "rank": 5.2, "score": 3764 }
      ,{ "datetime": "1900-01-06 06:51:54", "days": 6, "rank": 5.4, "score": 3673 }
      ,{ "datetime": "1900-01-06 05:19:49", "days": 6, "rank": 5.95, "score": 3433 }
      ,{ "datetime": "1900-01-06 06:16:29", "days": 6, "rank": 6.15, "score": 3374 }
      ,{ "datetime": "1900-01-06 08:22:27", "days": 6, "rank": 6.25, "score": 3338 }
      ,{ "datetime": "1900-01-06 08:15:56", "days": 6, "rank": 6.4, "score": 3283 }
      
      ,{ "datetime": "1900-01-06 11:47:19", "days": 6, "rank": 7.35, "score": 2992 }
      ,{ "datetime": "1900-01-06 12:56:17", "days": 6, "rank": 7.4, "score": 2975 }
      ,{ "datetime": "1900-01-06 12:35:30", "days": 6, "rank": 7.52, "score": 2939 }
      ,{ "datetime": "1900-01-06 09:26:24", "days": 6, "rank": 7.8, "score": 2858 }
      
      ,{ "datetime": "1900-01-06 11:57:14", "days": 6, "rank": 8.05, "score": 2793 }
      ,{ "datetime": "1900-01-06 09:55:50", "days": 6, "rank": 8.11, "score": 2777 }
      ,{ "datetime": "1900-01-06 11:05:04", "days": 6, "rank": 8.16, "score": 2765 }
      ,{ "datetime": "1900-01-06 13:36:45", "days": 6, "rank": 8.29, "score": 2733 }
      ,{ "datetime": "1900-01-06 09:45:39", "days": 6, "rank": 8.43, "score": 2694 }
      ,{ "datetime": "1900-01-06 08:34:43", "days": 6, "rank": 8.57, "score": 2661 }
      ,{ "datetime": "1900-01-06 11:48:40", "days": 6, "rank": 8.69, "score": 2632 }
      ,{ "datetime": "1900-01-06 11:42:46", "days": 6, "rank": 8.72, "score": 2624 }
      ,{ "datetime": "1900-01-06 12:34:12", "days": 6, "rank": 8.87, "score": 2587 }
      ,{ "datetime": "1900-01-06 09:16:50", "days": 6, "rank": 9.08, "score": 2540 }
      ,{ "datetime": "1900-01-06 11:34:36", "days": 6, "rank": 9.37, "score": 2473 }
      ,{ "datetime": "1900-01-06 06:13:44", "days": 6, "rank": 9.42, "score": 2462 }
      ,{ "datetime": "1900-01-06 05:48:30", "days": 6, "rank": 9.69, "score": 2403 }
      ,{ "datetime": "1900-01-06 06:51:05", "days": 6, "rank": 9.74, "score": 2393 }
      ,{ "datetime": "1900-01-06 06:40:42", "days": 6, "rank": 9.81, "score": 2378 }
      ,{ "datetime": "1900-01-06 09:23:00", "days": 6, "rank": 9.98, "score": 2341 }
      ,{ "datetime": "1900-01-06 08:43:23", "days": 6, "rank": 10, "score": 2337 }
      ,{ "datetime": "1900-01-06 11:36:45", "days": 6, "rank": 10.58, "score": 2221 }
      ,{ "datetime": "1900-01-06 11:37:59", "days": 6, "rank": 10.8, "score": 2179 }
      ,{ "datetime": "1900-01-06 11:17:09", "days": 6, "rank": 13.63, "score": 1691 }
      ,{ "datetime": "1900-01-06 05:12:34", "days": 6, "rank": 18.44, "score": 1100 }
      ,{ "datetime": "1900-01-06 12:56:17", "days": 6, "rank": 19.77, "score": 973 }
      ,{ "datetime": "1900-01-06 08:43:23", "days": 6, "rank": 20, "score": 953 }
      ,{ "datetime": "1900-01-06 08:50:28", "days": 6, "rank": 22.74, "score": 719 }
    ]
  }
]  